import com.mg.smsgame.MGMIDlet;
import java.io.InputStream;

final class ky implements Runnable, kn {
  public kq b;
  
  public kp c;
  
  public ko d;
  
  private kv e;
  
  private boolean f = false;
  
  public ky(InputStream paramInputStream) {
    this.e = new kv(paramInputStream);
    this.f = false;
    (new Thread(this)).start();
  }
  
  public final void run() {
    // Byte code:
    //   0: bipush #10
    //   2: istore_1
    //   3: aload_0
    //   4: iconst_0
    //   5: putfield f : Z
    //   8: goto -> 4330
    //   11: aload_0
    //   12: dup
    //   13: astore_2
    //   14: getfield e : Lkv;
    //   17: ifnonnull -> 29
    //   20: ldc '[SocketReader] input null'
    //   22: invokestatic a : (Ljava/lang/String;)V
    //   25: aconst_null
    //   26: goto -> 293
    //   29: aload_2
    //   30: getfield e : Lkv;
    //   33: astore_3
    //   34: bipush #7
    //   36: newarray byte
    //   38: astore #4
    //   40: aload_3
    //   41: getfield a : Ljava/io/InputStream;
    //   44: aload #4
    //   46: astore #10
    //   48: dup
    //   49: astore_2
    //   50: aload #10
    //   52: iconst_0
    //   53: invokestatic a : (Ljava/io/InputStream;[BI)I
    //   56: istore_2
    //   57: new ku
    //   60: dup
    //   61: invokespecial <init> : ()V
    //   64: astore #5
    //   66: iload_2
    //   67: ifgt -> 79
    //   70: ldc '[InputBuffer] readPacket() PACKET_FAIL'
    //   72: invokestatic a : (Ljava/lang/String;)V
    //   75: aconst_null
    //   76: goto -> 293
    //   79: getstatic ks.h : I
    //   82: iload_2
    //   83: iadd
    //   84: putstatic ks.h : I
    //   87: aload #4
    //   89: iconst_0
    //   90: baload
    //   91: aload #4
    //   93: iconst_1
    //   94: baload
    //   95: invokestatic a : (BB)I
    //   98: istore #6
    //   100: aload #4
    //   102: iconst_2
    //   103: baload
    //   104: aload #4
    //   106: iconst_3
    //   107: baload
    //   108: aload #4
    //   110: iconst_4
    //   111: baload
    //   112: aload #4
    //   114: iconst_5
    //   115: baload
    //   116: invokestatic a : (BBBB)I
    //   119: istore #7
    //   121: aload #5
    //   123: iload #7
    //   125: putfield a : I
    //   128: aload #4
    //   130: bipush #6
    //   132: baload
    //   133: invokestatic a : (B)I
    //   136: istore_2
    //   137: aload #5
    //   139: iload_2
    //   140: putfield b : I
    //   143: iload #7
    //   145: ifle -> 291
    //   148: getstatic ks.h : I
    //   151: iload #7
    //   153: iadd
    //   154: putstatic ks.h : I
    //   157: iload #6
    //   159: anewarray kt
    //   162: astore #4
    //   164: iconst_0
    //   165: istore #6
    //   167: goto -> 276
    //   170: iconst_5
    //   171: newarray byte
    //   173: astore #7
    //   175: aload_3
    //   176: getfield a : Ljava/io/InputStream;
    //   179: aload #7
    //   181: astore #10
    //   183: dup
    //   184: astore_2
    //   185: aload #10
    //   187: iconst_0
    //   188: invokestatic a : (Ljava/io/InputStream;[BI)I
    //   191: ifge -> 198
    //   194: aconst_null
    //   195: goto -> 293
    //   198: aload #7
    //   200: iconst_0
    //   201: baload
    //   202: invokestatic a : (B)I
    //   205: i2s
    //   206: istore #8
    //   208: aload #7
    //   210: iconst_1
    //   211: baload
    //   212: aload #7
    //   214: iconst_2
    //   215: baload
    //   216: aload #7
    //   218: iconst_3
    //   219: baload
    //   220: aload #7
    //   222: iconst_4
    //   223: baload
    //   224: invokestatic a : (BBBB)I
    //   227: dup
    //   228: istore #7
    //   230: newarray byte
    //   232: astore #9
    //   234: aload_3
    //   235: getfield a : Ljava/io/InputStream;
    //   238: aload #9
    //   240: astore #10
    //   242: dup
    //   243: astore_2
    //   244: aload #10
    //   246: iconst_0
    //   247: invokestatic a : (Ljava/io/InputStream;[BI)I
    //   250: ifge -> 257
    //   253: aconst_null
    //   254: goto -> 293
    //   257: aload #4
    //   259: iload #6
    //   261: new kt
    //   264: dup
    //   265: iload #8
    //   267: aload #9
    //   269: invokespecial <init> : (S[B)V
    //   272: aastore
    //   273: iinc #6, 1
    //   276: iload #6
    //   278: aload #4
    //   280: arraylength
    //   281: if_icmplt -> 170
    //   284: aload #5
    //   286: aload #4
    //   288: putfield c : [Lkt;
    //   291: aload #5
    //   293: dup
    //   294: astore_2
    //   295: ifnonnull -> 326
    //   298: iinc #1, -1
    //   301: iload_1
    //   302: ifgt -> 313
    //   305: aload_0
    //   306: iconst_1
    //   307: putfield f : Z
    //   310: goto -> 364
    //   313: ldc2_w 3000
    //   316: invokestatic sleep : (J)V
    //   319: goto -> 364
    //   322: pop
    //   323: goto -> 364
    //   326: bipush #10
    //   328: istore_1
    //   329: goto -> 364
    //   332: dup
    //   333: astore_2
    //   334: invokevirtual printStackTrace : ()V
    //   337: iinc #1, -1
    //   340: iload_1
    //   341: ifgt -> 352
    //   344: aload_0
    //   345: iconst_1
    //   346: putfield f : Z
    //   349: goto -> 362
    //   352: ldc2_w 1000
    //   355: invokestatic sleep : (J)V
    //   358: goto -> 362
    //   361: pop
    //   362: aconst_null
    //   363: astore_2
    //   364: aload_0
    //   365: aload_2
    //   366: astore_3
    //   367: astore_2
    //   368: aload_3
    //   369: ifnonnull -> 380
    //   372: ldc '[PAT] Get NULL packet on SocketReader.process()'
    //   374: invokestatic a : (Ljava/lang/String;)V
    //   377: goto -> 4330
    //   380: aload_2
    //   381: getfield b : Lkq;
    //   384: ifnonnull -> 397
    //   387: new java/lang/NullPointerException
    //   390: dup
    //   391: ldc 'Main listener can't be NULL'
    //   393: invokespecial <init> : (Ljava/lang/String;)V
    //   396: athrow
    //   397: aload_3
    //   398: getfield b : I
    //   401: i2s
    //   402: dup
    //   403: istore #4
    //   405: tableswitch default -> 4321, 0 -> 956, 1 -> 1077, 2 -> 1087, 3 -> 1109, 4 -> 3353, 5 -> 1101, 6 -> 1487, 7 -> 2822, 8 -> 1153, 9 -> 1161, 10 -> 1266, 11 -> 1471, 12 -> 2423, 13 -> 1602, 14 -> 4321, 15 -> 4321, 16 -> 1650, 17 -> 1681, 18 -> 1801, 19 -> 1880, 20 -> 2140, 21 -> 2588, 22 -> 1793, 23 -> 2636, 24 -> 2029, 25 -> 2372, 26 -> 4321, 27 -> 1283, 28 -> 2624, 29 -> 1221, 30 -> 1213, 31 -> 2644, 32 -> 2652, 33 -> 2676, 34 -> 2691, 35 -> 2746, 36 -> 1295, 37 -> 1311, 38 -> 2684, 39 -> 4321, 40 -> 2314, 41 -> 2664, 42 -> 1303, 43 -> 1479, 44 -> 2148, 45 -> 2754, 46 -> 2771, 47 -> 2210, 48 -> 1423, 49 -> 4321, 50 -> 4321, 51 -> 3372, 52 -> 2946, 53 -> 4321, 54 -> 4321, 55 -> 2798, 56 -> 2806, 57 -> 2814, 58 -> 4321, 59 -> 4321, 60 -> 4321, 61 -> 4321, 62 -> 4321, 63 -> 4321, 64 -> 3187, 65 -> 3195, 66 -> 4321, 67 -> 4321, 68 -> 4321, 69 -> 4321, 70 -> 4321, 71 -> 4321, 72 -> 4321, 73 -> 4321, 74 -> 4321, 75 -> 4321, 76 -> 4321, 77 -> 4321, 78 -> 4321, 79 -> 4321, 80 -> 4321, 81 -> 4321, 82 -> 4321, 83 -> 3499, 84 -> 2271, 85 -> 4321, 86 -> 4321, 87 -> 4321, 88 -> 4321, 89 -> 4321, 90 -> 4321, 91 -> 4321, 92 -> 4321, 93 -> 4321, 94 -> 4321, 95 -> 4321, 96 -> 3796, 97 -> 3885, 98 -> 4083, 99 -> 3537, 100 -> 3616, 101 -> 3788, 102 -> 4321, 103 -> 4321, 104 -> 4321, 105 -> 4321, 106 -> 4321, 107 -> 4321, 108 -> 4321, 109 -> 4321, 110 -> 4321, 111 -> 4321, 112 -> 4091, 113 -> 4201, 114 -> 4209, 115 -> 4283, 116 -> 4193, 117 -> 4321, 118 -> 4321, 119 -> 4321, 120 -> 4321, 121 -> 4321, 122 -> 4321, 123 -> 4321, 124 -> 4321, 125 -> 2926, 126 -> 4321, 127 -> 4321, 128 -> 2954, 129 -> 2971, 130 -> 3285, 131 -> 3321, 132 -> 4291, 133 -> 4299
    //   956: aload_2
    //   957: aload_3
    //   958: astore_3
    //   959: astore_2
    //   960: aload_3
    //   961: iconst_0
    //   962: iconst_m1
    //   963: invokevirtual a : (SB)B
    //   966: istore #4
    //   968: aload_3
    //   969: iconst_1
    //   970: invokevirtual d : (S)Ljava/lang/String;
    //   973: astore #5
    //   975: iload #4
    //   977: tableswitch default -> 1061, 3 -> 1035, 4 -> 1061, 5 -> 1061, 6 -> 1061, 7 -> 1016, 8 -> 1047
    //   1016: aload_2
    //   1017: getfield c : Lkp;
    //   1020: ifnull -> 1074
    //   1023: aload_2
    //   1024: getfield c : Lkp;
    //   1027: invokeinterface a : ()V
    //   1032: goto -> 4330
    //   1035: aload_2
    //   1036: getfield b : Lkq;
    //   1039: invokeinterface w : ()V
    //   1044: goto -> 4330
    //   1047: aload_2
    //   1048: getfield b : Lkq;
    //   1051: aload #5
    //   1053: invokeinterface b : (Ljava/lang/String;)V
    //   1058: goto -> 4330
    //   1061: aload_2
    //   1062: getfield b : Lkq;
    //   1065: iload #4
    //   1067: aload #5
    //   1069: invokeinterface a : (ILjava/lang/String;)V
    //   1074: goto -> 4330
    //   1077: invokestatic a : ()Lks;
    //   1080: iconst_3
    //   1081: putfield b : I
    //   1084: goto -> 4330
    //   1087: invokestatic a : ()Lks;
    //   1090: aload_3
    //   1091: iconst_3
    //   1092: invokevirtual d : (S)Ljava/lang/String;
    //   1095: invokevirtual a : (Ljava/lang/String;)V
    //   1098: goto -> 4330
    //   1101: aload_2
    //   1102: aload_3
    //   1103: invokespecial c : (Lku;)V
    //   1106: goto -> 4330
    //   1109: aload_3
    //   1110: iconst_2
    //   1111: invokevirtual c : (S)[B
    //   1114: astore_2
    //   1115: invokestatic a : ()Lks;
    //   1118: getfield c : Ljava/lang/String;
    //   1121: astore #5
    //   1123: invokestatic a : ()Lks;
    //   1126: getfield d : Ljava/lang/String;
    //   1129: astore #6
    //   1131: aload_2
    //   1132: aload #6
    //   1134: invokestatic a : ([BLjava/lang/String;)[B
    //   1137: astore #7
    //   1139: invokestatic a : ()Lks;
    //   1142: aload #5
    //   1144: aload #7
    //   1146: aload_2
    //   1147: invokevirtual a : (Ljava/lang/String;[B[B)V
    //   1150: goto -> 4330
    //   1153: aload_2
    //   1154: aload_3
    //   1155: invokespecial e : (Lku;)V
    //   1158: goto -> 4330
    //   1161: aload_3
    //   1162: bipush #112
    //   1164: invokevirtual c : (S)[B
    //   1167: pop
    //   1168: aload_3
    //   1169: sipush #134
    //   1172: iconst_m1
    //   1173: invokevirtual a : (SB)B
    //   1176: dup
    //   1177: istore #4
    //   1179: ifle -> 1205
    //   1182: aload_2
    //   1183: aload_3
    //   1184: invokespecial a : (Lku;)Llh;
    //   1187: astore #6
    //   1189: aload_2
    //   1190: getfield b : Lkq;
    //   1193: aload #6
    //   1195: iload #4
    //   1197: invokeinterface a : (Llh;B)V
    //   1202: goto -> 4330
    //   1205: aload_2
    //   1206: aload_3
    //   1207: invokespecial b : (Lku;)V
    //   1210: goto -> 4330
    //   1213: aload_2
    //   1214: aload_3
    //   1215: invokespecial q : (Lku;)V
    //   1218: goto -> 4330
    //   1221: aload_3
    //   1222: bipush #9
    //   1224: invokevirtual d : (S)Ljava/lang/String;
    //   1227: astore #6
    //   1229: aload_3
    //   1230: bipush #20
    //   1232: invokevirtual d : (S)Ljava/lang/String;
    //   1235: astore #7
    //   1237: aload_3
    //   1238: bipush #21
    //   1240: iconst_0
    //   1241: iconst_m1
    //   1242: iconst_0
    //   1243: invokevirtual a : (SIII)I
    //   1246: istore #8
    //   1248: aload_2
    //   1249: getfield b : Lkq;
    //   1252: aload #6
    //   1254: aload #7
    //   1256: iload #8
    //   1258: invokeinterface a : (Ljava/lang/String;Ljava/lang/String;I)V
    //   1263: goto -> 4330
    //   1266: aload_2
    //   1267: aload_3
    //   1268: invokespecial b : (Lku;)V
    //   1271: aload_2
    //   1272: getfield b : Lkq;
    //   1275: invokeinterface U : ()V
    //   1280: goto -> 4330
    //   1283: aload_2
    //   1284: getfield b : Lkq;
    //   1287: invokeinterface U : ()V
    //   1292: goto -> 4330
    //   1295: aload_2
    //   1296: aload_3
    //   1297: invokespecial C : (Lku;)V
    //   1300: goto -> 4330
    //   1303: aload_2
    //   1304: aload_3
    //   1305: invokespecial r : (Lku;)V
    //   1308: goto -> 4330
    //   1311: aload_3
    //   1312: bipush #89
    //   1314: iconst_m1
    //   1315: invokevirtual a : (SB)B
    //   1318: dup
    //   1319: istore #7
    //   1321: ifne -> 1332
    //   1324: aload_2
    //   1325: aload_3
    //   1326: invokespecial b : (Lku;)V
    //   1329: goto -> 4330
    //   1332: iload #7
    //   1334: iconst_1
    //   1335: if_icmpeq -> 1344
    //   1338: iload #7
    //   1340: iconst_2
    //   1341: if_icmpne -> 4330
    //   1344: aload_3
    //   1345: bipush #83
    //   1347: invokevirtual b : (S)I
    //   1350: anewarray java/lang/String
    //   1353: astore #9
    //   1355: iconst_0
    //   1356: istore #4
    //   1358: goto -> 1381
    //   1361: aload #9
    //   1363: iload #4
    //   1365: aload_3
    //   1366: aload_3
    //   1367: bipush #83
    //   1369: iload #4
    //   1371: invokevirtual b : (SI)I
    //   1374: invokevirtual b : (I)Ljava/lang/String;
    //   1377: aastore
    //   1378: iinc #4, 1
    //   1381: iload #4
    //   1383: aload #9
    //   1385: arraylength
    //   1386: if_icmplt -> 1361
    //   1389: iload #7
    //   1391: iconst_1
    //   1392: if_icmpne -> 1409
    //   1395: aload_2
    //   1396: getfield b : Lkq;
    //   1399: aload #9
    //   1401: invokeinterface c : ([Ljava/lang/String;)V
    //   1406: goto -> 4330
    //   1409: aload_2
    //   1410: getfield b : Lkq;
    //   1413: aload #9
    //   1415: invokeinterface d : ([Ljava/lang/String;)V
    //   1420: goto -> 4330
    //   1423: aload_2
    //   1424: aload_3
    //   1425: astore_3
    //   1426: astore_2
    //   1427: aload_3
    //   1428: bipush #83
    //   1430: invokevirtual d : (S)Ljava/lang/String;
    //   1433: astore #4
    //   1435: aload_3
    //   1436: bipush #114
    //   1438: iconst_m1
    //   1439: invokevirtual c : (SI)I
    //   1442: istore #5
    //   1444: aload_3
    //   1445: bipush #106
    //   1447: iconst_m1
    //   1448: invokevirtual c : (SI)I
    //   1451: istore #23
    //   1453: aload_2
    //   1454: getfield b : Lkq;
    //   1457: aload #4
    //   1459: iload #5
    //   1461: iload #23
    //   1463: invokeinterface b : (Ljava/lang/String;II)V
    //   1468: goto -> 4330
    //   1471: aload_2
    //   1472: aload_3
    //   1473: invokespecial d : (Lku;)V
    //   1476: goto -> 4330
    //   1479: aload_2
    //   1480: aload_3
    //   1481: invokespecial f : (Lku;)V
    //   1484: goto -> 4330
    //   1487: aload_2
    //   1488: aload_3
    //   1489: astore_3
    //   1490: astore_2
    //   1491: aload_3
    //   1492: iconst_4
    //   1493: iconst_0
    //   1494: invokevirtual c : (SI)I
    //   1497: istore #4
    //   1499: aload_3
    //   1500: aload_3
    //   1501: bipush #7
    //   1503: iconst_0
    //   1504: invokevirtual b : (SI)I
    //   1507: iconst_m1
    //   1508: invokevirtual a : (II)I
    //   1511: dup
    //   1512: istore #5
    //   1514: ifge -> 1569
    //   1517: aload_3
    //   1518: aload_3
    //   1519: bipush #6
    //   1521: iconst_0
    //   1522: invokevirtual b : (SI)I
    //   1525: iconst_m1
    //   1526: invokevirtual a : (II)I
    //   1529: istore #23
    //   1531: aload_3
    //   1532: aload_3
    //   1533: iconst_5
    //   1534: iconst_0
    //   1535: invokevirtual b : (SI)I
    //   1538: iconst_m1
    //   1539: invokevirtual a : (II)I
    //   1542: istore #24
    //   1544: aload_2
    //   1545: getfield d : Lko;
    //   1548: ifnull -> 1599
    //   1551: aload_2
    //   1552: getfield d : Lko;
    //   1555: iload #4
    //   1557: iload #23
    //   1559: iload #24
    //   1561: invokeinterface a : (III)V
    //   1566: goto -> 4330
    //   1569: aload_3
    //   1570: bipush #8
    //   1572: invokevirtual c : (S)[B
    //   1575: astore #23
    //   1577: aload_2
    //   1578: getfield d : Lko;
    //   1581: ifnull -> 1599
    //   1584: aload_2
    //   1585: getfield d : Lko;
    //   1588: iload #4
    //   1590: iload #5
    //   1592: aload #23
    //   1594: invokeinterface a : (II[B)V
    //   1599: goto -> 4330
    //   1602: aload_2
    //   1603: aload_3
    //   1604: astore_3
    //   1605: astore_2
    //   1606: aload_3
    //   1607: bipush #20
    //   1609: invokevirtual d : (S)Ljava/lang/String;
    //   1612: astore #4
    //   1614: aload_3
    //   1615: bipush #21
    //   1617: iconst_0
    //   1618: invokevirtual c : (SI)I
    //   1621: istore #5
    //   1623: aload_3
    //   1624: bipush #22
    //   1626: iconst_0
    //   1627: invokevirtual a : (SB)B
    //   1630: istore #23
    //   1632: aload_2
    //   1633: getfield b : Lkq;
    //   1636: aload #4
    //   1638: iload #5
    //   1640: iload #23
    //   1642: invokeinterface a : (Ljava/lang/String;II)V
    //   1647: goto -> 4330
    //   1650: aload_3
    //   1651: bipush #9
    //   1653: invokevirtual d : (S)Ljava/lang/String;
    //   1656: astore #6
    //   1658: aload_3
    //   1659: iconst_1
    //   1660: invokevirtual d : (S)Ljava/lang/String;
    //   1663: astore #9
    //   1665: aload_2
    //   1666: getfield b : Lkq;
    //   1669: aload #6
    //   1671: aload #9
    //   1673: invokeinterface b : (Ljava/lang/String;Ljava/lang/String;)V
    //   1678: goto -> 4330
    //   1681: aload_2
    //   1682: aload_3
    //   1683: astore_3
    //   1684: astore_2
    //   1685: aload_3
    //   1686: bipush #28
    //   1688: invokevirtual d : (S)Ljava/lang/String;
    //   1691: astore #4
    //   1693: aload_3
    //   1694: bipush #9
    //   1696: invokevirtual d : (S)Ljava/lang/String;
    //   1699: astore #5
    //   1701: aload_3
    //   1702: iconst_1
    //   1703: invokevirtual d : (S)Ljava/lang/String;
    //   1706: astore #23
    //   1708: aload_2
    //   1709: aload_3
    //   1710: iconst_0
    //   1711: iconst_m1
    //   1712: invokespecial a : (Lku;II)Llh;
    //   1715: dup
    //   1716: astore #24
    //   1718: aload #5
    //   1720: putfield b : Ljava/lang/String;
    //   1723: aload_3
    //   1724: sipush #132
    //   1727: lconst_0
    //   1728: invokevirtual a : (SJ)J
    //   1731: lstore #25
    //   1733: aload_3
    //   1734: sipush #167
    //   1737: iconst_0
    //   1738: invokevirtual a : (SB)B
    //   1741: istore #27
    //   1743: aload_3
    //   1744: sipush #169
    //   1747: iconst_0
    //   1748: invokevirtual a : (SB)B
    //   1751: istore #6
    //   1753: aload_2
    //   1754: getfield b : Lkq;
    //   1757: aload #24
    //   1759: aload #23
    //   1761: lload #25
    //   1763: aload #4
    //   1765: iload #27
    //   1767: ifle -> 1774
    //   1770: iconst_1
    //   1771: goto -> 1775
    //   1774: iconst_0
    //   1775: iload #6
    //   1777: ifle -> 1784
    //   1780: iconst_1
    //   1781: goto -> 1785
    //   1784: iconst_0
    //   1785: invokeinterface a : (Llh;Ljava/lang/String;JLjava/lang/String;ZZ)V
    //   1790: goto -> 4330
    //   1793: aload_2
    //   1794: aload_3
    //   1795: invokespecial j : (Lku;)V
    //   1798: goto -> 4330
    //   1801: aload_2
    //   1802: aload_3
    //   1803: astore_3
    //   1804: astore_2
    //   1805: aload_3
    //   1806: bipush #41
    //   1808: iconst_0
    //   1809: invokevirtual c : (SI)I
    //   1812: istore #4
    //   1814: new nq
    //   1817: dup
    //   1818: iload #4
    //   1820: iconst_0
    //   1821: invokespecial <init> : (IB)V
    //   1824: astore #5
    //   1826: aload_3
    //   1827: bipush #32
    //   1829: invokevirtual a : (S)Z
    //   1832: istore #23
    //   1834: aload_3
    //   1835: bipush #39
    //   1837: invokevirtual a : (S)Z
    //   1840: ifeq -> 1852
    //   1843: aload #5
    //   1845: iconst_1
    //   1846: putfield E : Z
    //   1849: goto -> 1859
    //   1852: aload #5
    //   1854: iload #23
    //   1856: putfield d : Z
    //   1859: aload_2
    //   1860: getfield c : Lkp;
    //   1863: ifnull -> 1877
    //   1866: aload_2
    //   1867: getfield c : Lkp;
    //   1870: aload #5
    //   1872: invokeinterface a : (Lnq;)V
    //   1877: goto -> 4330
    //   1880: aload_2
    //   1881: aload_3
    //   1882: astore_3
    //   1883: astore_2
    //   1884: aload_3
    //   1885: bipush #41
    //   1887: iconst_0
    //   1888: invokevirtual c : (SI)I
    //   1891: istore #4
    //   1893: new nq
    //   1896: dup
    //   1897: iload #4
    //   1899: iconst_3
    //   1900: invokespecial <init> : (IB)V
    //   1903: dup
    //   1904: astore #5
    //   1906: aload_3
    //   1907: bipush #44
    //   1909: lconst_0
    //   1910: invokevirtual a : (SJ)J
    //   1913: putfield i : J
    //   1916: aload_3
    //   1917: aload_3
    //   1918: bipush #33
    //   1920: iconst_0
    //   1921: invokevirtual b : (SI)I
    //   1924: iconst_m1
    //   1925: invokevirtual a : (II)I
    //   1928: istore #23
    //   1930: aload_3
    //   1931: aload_3
    //   1932: bipush #34
    //   1934: iconst_0
    //   1935: invokevirtual b : (SI)I
    //   1938: iconst_m1
    //   1939: invokevirtual a : (II)I
    //   1942: istore #24
    //   1944: aload_3
    //   1945: aload_3
    //   1946: bipush #33
    //   1948: iconst_1
    //   1949: invokevirtual b : (SI)I
    //   1952: iconst_m1
    //   1953: invokevirtual a : (II)I
    //   1956: istore #25
    //   1958: aload_3
    //   1959: aload_3
    //   1960: bipush #34
    //   1962: iconst_1
    //   1963: invokevirtual b : (SI)I
    //   1966: iconst_m1
    //   1967: invokevirtual a : (II)I
    //   1970: istore #26
    //   1972: aload #5
    //   1974: iload #23
    //   1976: iload #24
    //   1978: iload #25
    //   1980: iload #26
    //   1982: istore #8
    //   1984: istore #7
    //   1986: istore #4
    //   1988: istore #6
    //   1990: dup
    //   1991: astore #27
    //   1993: iload #6
    //   1995: putfield j : I
    //   1998: aload #27
    //   2000: iload #7
    //   2002: putfield l : I
    //   2005: aload #27
    //   2007: iload #4
    //   2009: putfield k : I
    //   2012: aload #27
    //   2014: iload #8
    //   2016: putfield m : I
    //   2019: aload_2
    //   2020: aload_3
    //   2021: aload #5
    //   2023: invokespecial a : (Lku;Lnq;)V
    //   2026: goto -> 4330
    //   2029: aload_2
    //   2030: aload_3
    //   2031: astore_3
    //   2032: astore_2
    //   2033: ldc '[processUpdateMatch]======================================'
    //   2035: invokestatic a : (Ljava/lang/String;)V
    //   2038: aload_3
    //   2039: bipush #41
    //   2041: iconst_0
    //   2042: invokevirtual c : (SI)I
    //   2045: istore #4
    //   2047: new nq
    //   2050: dup
    //   2051: iload #4
    //   2053: iconst_2
    //   2054: invokespecial <init> : (IB)V
    //   2057: astore #5
    //   2059: aload_3
    //   2060: aload #5
    //   2062: invokestatic b : (Lku;Lnq;)V
    //   2065: aload_3
    //   2066: bipush #32
    //   2068: invokevirtual a : (S)Z
    //   2071: istore #23
    //   2073: aload_3
    //   2074: bipush #39
    //   2076: invokevirtual c : (S)[B
    //   2079: dup
    //   2080: astore #24
    //   2082: ifnull -> 2119
    //   2085: aload_2
    //   2086: getfield c : Lkp;
    //   2089: aload #5
    //   2091: invokeinterface a : (Lnq;)V
    //   2096: aload #5
    //   2098: iconst_1
    //   2099: putfield E : Z
    //   2102: aload_2
    //   2103: aload_3
    //   2104: aload #24
    //   2106: iconst_0
    //   2107: baload
    //   2108: aload #5
    //   2110: getfield b : I
    //   2113: invokespecial a : (Lku;BI)V
    //   2116: goto -> 4330
    //   2119: aload #5
    //   2121: iload #23
    //   2123: putfield d : Z
    //   2126: aload_2
    //   2127: getfield c : Lkp;
    //   2130: aload #5
    //   2132: invokeinterface a : (Lnq;)V
    //   2137: goto -> 4330
    //   2140: aload_2
    //   2141: aload_3
    //   2142: invokespecial m : (Lku;)V
    //   2145: goto -> 4330
    //   2148: aload_2
    //   2149: aload_3
    //   2150: astore_3
    //   2151: astore_2
    //   2152: aload_3
    //   2153: bipush #41
    //   2155: iconst_0
    //   2156: invokevirtual c : (SI)I
    //   2159: istore #4
    //   2161: new nq
    //   2164: dup
    //   2165: iload #4
    //   2167: iconst_4
    //   2168: invokespecial <init> : (IB)V
    //   2171: dup
    //   2172: astore #5
    //   2174: aload_3
    //   2175: bipush #44
    //   2177: lconst_0
    //   2178: invokevirtual a : (SJ)J
    //   2181: putfield i : J
    //   2184: aload_3
    //   2185: bipush #114
    //   2187: iconst_0
    //   2188: invokevirtual c : (SI)I
    //   2191: istore #23
    //   2193: aload #5
    //   2195: iload #23
    //   2197: putfield e : I
    //   2200: aload_2
    //   2201: aload_3
    //   2202: aload #5
    //   2204: invokespecial a : (Lku;Lnq;)V
    //   2207: goto -> 4330
    //   2210: aload_2
    //   2211: getfield c : Lkp;
    //   2214: ifnull -> 4330
    //   2217: new nq
    //   2220: dup
    //   2221: iconst_1
    //   2222: invokespecial <init> : (B)V
    //   2225: dup
    //   2226: astore #4
    //   2228: aload_3
    //   2229: bipush #34
    //   2231: iconst_2
    //   2232: invokevirtual c : (SI)I
    //   2235: putfield k : I
    //   2238: aload #4
    //   2240: aload_3
    //   2241: bipush #33
    //   2243: iconst_2
    //   2244: invokevirtual c : (SI)I
    //   2247: putfield j : I
    //   2250: aload_2
    //   2251: getfield c : Lkp;
    //   2254: ifnull -> 4330
    //   2257: aload_2
    //   2258: getfield c : Lkp;
    //   2261: aload #4
    //   2263: invokeinterface a : (Lnq;)V
    //   2268: goto -> 4330
    //   2271: aload_2
    //   2272: aload_3
    //   2273: astore_3
    //   2274: astore_2
    //   2275: aload_3
    //   2276: bipush #114
    //   2278: iconst_m1
    //   2279: invokevirtual c : (SI)I
    //   2282: istore #4
    //   2284: aload_3
    //   2285: bipush #106
    //   2287: iconst_m1
    //   2288: invokevirtual c : (SI)I
    //   2291: istore #5
    //   2293: aload_2
    //   2294: getfield b : Lkq;
    //   2297: iload #4
    //   2299: iload #5
    //   2301: invokeinterface e : (II)V
    //   2306: aload_2
    //   2307: aload_3
    //   2308: invokespecial b : (Lku;)V
    //   2311: goto -> 4330
    //   2314: aload_2
    //   2315: getfield c : Lkp;
    //   2318: ifnull -> 4330
    //   2321: aload_3
    //   2322: bipush #39
    //   2324: invokevirtual c : (S)[B
    //   2327: dup
    //   2328: astore #4
    //   2330: ifnonnull -> 2346
    //   2333: aload_2
    //   2334: getfield c : Lkp;
    //   2337: iconst_m1
    //   2338: invokeinterface a : (I)V
    //   2343: goto -> 4330
    //   2346: aload_2
    //   2347: getfield c : Lkp;
    //   2350: aload #4
    //   2352: iconst_0
    //   2353: baload
    //   2354: invokeinterface a : (I)V
    //   2359: aload_2
    //   2360: aload_3
    //   2361: aload #4
    //   2363: iconst_0
    //   2364: baload
    //   2365: iconst_m1
    //   2366: invokespecial a : (Lku;BI)V
    //   2369: goto -> 4330
    //   2372: aload_3
    //   2373: bipush #9
    //   2375: invokevirtual d : (S)Ljava/lang/String;
    //   2378: astore #6
    //   2380: aload_3
    //   2381: iconst_1
    //   2382: invokevirtual d : (S)Ljava/lang/String;
    //   2385: astore #9
    //   2387: aload_2
    //   2388: getfield c : Lkp;
    //   2391: ifnull -> 2407
    //   2394: aload_2
    //   2395: getfield c : Lkp;
    //   2398: aload #6
    //   2400: aload #9
    //   2402: invokeinterface a : (Ljava/lang/String;Ljava/lang/String;)V
    //   2407: aload_2
    //   2408: getfield b : Lkq;
    //   2411: aload #6
    //   2413: aload #9
    //   2415: invokeinterface c : (Ljava/lang/String;Ljava/lang/String;)V
    //   2420: goto -> 4330
    //   2423: aload_2
    //   2424: aload_3
    //   2425: astore_3
    //   2426: astore_2
    //   2427: aload_3
    //   2428: sipush #192
    //   2431: invokevirtual d : (S)Ljava/lang/String;
    //   2434: astore #4
    //   2436: aload_3
    //   2437: iconst_1
    //   2438: invokevirtual d : (S)Ljava/lang/String;
    //   2441: astore #5
    //   2443: aload_3
    //   2444: sipush #157
    //   2447: iconst_0
    //   2448: invokevirtual c : (SI)I
    //   2451: i2l
    //   2452: lstore #23
    //   2454: aload_3
    //   2455: bipush #9
    //   2457: invokevirtual d : (S)Ljava/lang/String;
    //   2460: astore #25
    //   2462: aload_3
    //   2463: bipush #40
    //   2465: iconst_m1
    //   2466: invokevirtual a : (SB)B
    //   2469: dup
    //   2470: istore #26
    //   2472: tableswitch default -> 2585, 0 -> 2504, 1 -> 2520, 2 -> 2550, 3 -> 2580
    //   2504: aload_2
    //   2505: getfield b : Lkq;
    //   2508: aload #4
    //   2510: aload #25
    //   2512: invokeinterface a : (Ljava/lang/String;Ljava/lang/String;)V
    //   2517: goto -> 4330
    //   2520: aload_2
    //   2521: getfield b : Lkq;
    //   2524: aload #4
    //   2526: aload_3
    //   2527: aload_3
    //   2528: bipush #9
    //   2530: iconst_0
    //   2531: invokevirtual b : (SI)I
    //   2534: iconst_m1
    //   2535: invokestatic d : (Lku;II)Ldo;
    //   2538: aload #5
    //   2540: lload #23
    //   2542: invokeinterface a : (Ljava/lang/String;Ldo;Ljava/lang/String;J)V
    //   2547: goto -> 4330
    //   2550: aload_2
    //   2551: getfield b : Lkq;
    //   2554: aload #4
    //   2556: aload_3
    //   2557: aload_3
    //   2558: bipush #9
    //   2560: iconst_0
    //   2561: invokevirtual b : (SI)I
    //   2564: iconst_m1
    //   2565: invokestatic d : (Lku;II)Ldo;
    //   2568: aload #5
    //   2570: lload #23
    //   2572: invokeinterface b : (Ljava/lang/String;Ldo;Ljava/lang/String;J)V
    //   2577: goto -> 4330
    //   2580: aload_2
    //   2581: aload_3
    //   2582: invokespecial h : (Lku;)V
    //   2585: goto -> 4330
    //   2588: aload_2
    //   2589: aload_3
    //   2590: astore_3
    //   2591: astore_2
    //   2592: aload_3
    //   2593: bipush #41
    //   2595: iconst_0
    //   2596: invokevirtual c : (SI)I
    //   2599: istore #4
    //   2601: new nq
    //   2604: dup
    //   2605: iload #4
    //   2607: bipush #6
    //   2609: invokespecial <init> : (IB)V
    //   2612: astore #5
    //   2614: aload_2
    //   2615: aload_3
    //   2616: aload #5
    //   2618: invokespecial a : (Lku;Lnq;)V
    //   2621: goto -> 4330
    //   2624: aload_2
    //   2625: getfield b : Lkq;
    //   2628: invokeinterface V : ()V
    //   2633: goto -> 4330
    //   2636: aload_2
    //   2637: aload_3
    //   2638: invokespecial l : (Lku;)V
    //   2641: goto -> 4330
    //   2644: aload_2
    //   2645: aload_3
    //   2646: invokespecial g : (Lku;)V
    //   2649: goto -> 4330
    //   2652: aload_2
    //   2653: getfield b : Lkq;
    //   2656: invokeinterface A : ()V
    //   2661: goto -> 4330
    //   2664: aload_2
    //   2665: getfield b : Lkq;
    //   2668: invokeinterface B : ()V
    //   2673: goto -> 4330
    //   2676: aload_2
    //   2677: aload_3
    //   2678: invokespecial n : (Lku;)V
    //   2681: goto -> 4330
    //   2684: aload_3
    //   2685: invokestatic o : (Lku;)V
    //   2688: goto -> 4330
    //   2691: new nt
    //   2694: dup
    //   2695: aload_3
    //   2696: bipush #80
    //   2698: iconst_m1
    //   2699: invokevirtual c : (SI)I
    //   2702: aload_3
    //   2703: bipush #81
    //   2705: invokevirtual d : (S)Ljava/lang/String;
    //   2708: ldc ''
    //   2710: aload_3
    //   2711: bipush #77
    //   2713: invokevirtual d : (S)Ljava/lang/String;
    //   2716: invokespecial <init> : (ILjava/lang/String;Ljava/lang/String;Ljava/lang/String;)V
    //   2719: invokestatic a : (Lnt;)V
    //   2722: aload_3
    //   2723: sipush #149
    //   2726: invokevirtual d : (S)Ljava/lang/String;
    //   2729: astore #4
    //   2731: aload_2
    //   2732: getfield b : Lkq;
    //   2735: aload #4
    //   2737: iconst_0
    //   2738: invokeinterface a : (Ljava/lang/String;B)V
    //   2743: goto -> 4330
    //   2746: aload_2
    //   2747: aload_3
    //   2748: invokespecial p : (Lku;)V
    //   2751: goto -> 4330
    //   2754: aload_2
    //   2755: getfield b : Lkq;
    //   2758: aload_3
    //   2759: iconst_1
    //   2760: invokevirtual d : (S)Ljava/lang/String;
    //   2763: invokeinterface c : (Ljava/lang/String;)V
    //   2768: goto -> 4330
    //   2771: aload_2
    //   2772: getfield b : Lkq;
    //   2775: aload_3
    //   2776: bipush #9
    //   2778: invokevirtual d : (S)Ljava/lang/String;
    //   2781: pop
    //   2782: aload_3
    //   2783: sipush #132
    //   2786: lconst_0
    //   2787: invokevirtual a : (SJ)J
    //   2790: invokeinterface a : (J)V
    //   2795: goto -> 4330
    //   2798: aload_2
    //   2799: aload_3
    //   2800: invokespecial s : (Lku;)V
    //   2803: goto -> 4330
    //   2806: aload_2
    //   2807: aload_3
    //   2808: invokespecial v : (Lku;)V
    //   2811: goto -> 4330
    //   2814: aload_2
    //   2815: aload_3
    //   2816: invokespecial t : (Lku;)V
    //   2819: goto -> 4330
    //   2822: aload_2
    //   2823: aload_3
    //   2824: astore_3
    //   2825: astore_2
    //   2826: aload_3
    //   2827: sipush #147
    //   2830: iconst_m1
    //   2831: invokevirtual a : (SB)B
    //   2834: dup
    //   2835: istore #5
    //   2837: tableswitch default -> 2923, 0 -> 2860, 1 -> 2893
    //   2860: aload_3
    //   2861: sipush #165
    //   2864: iconst_m1
    //   2865: invokevirtual a : (SB)B
    //   2868: istore #4
    //   2870: aload_2
    //   2871: getfield b : Lkq;
    //   2874: iload #4
    //   2876: iconst_1
    //   2877: if_icmpne -> 2884
    //   2880: iconst_1
    //   2881: goto -> 2885
    //   2884: iconst_0
    //   2885: invokeinterface c : (Z)V
    //   2890: goto -> 4330
    //   2893: aload_3
    //   2894: sipush #166
    //   2897: iconst_m1
    //   2898: invokevirtual a : (SB)B
    //   2901: istore #4
    //   2903: aload_2
    //   2904: getfield b : Lkq;
    //   2907: iload #4
    //   2909: iconst_1
    //   2910: if_icmpne -> 2917
    //   2913: iconst_1
    //   2914: goto -> 2918
    //   2917: iconst_0
    //   2918: invokeinterface d : (Z)V
    //   2923: goto -> 4330
    //   2926: aload_2
    //   2927: getfield b : Lkq;
    //   2930: aload_3
    //   2931: sipush #149
    //   2934: invokevirtual d : (S)Ljava/lang/String;
    //   2937: iconst_0
    //   2938: invokeinterface a : (Ljava/lang/String;B)V
    //   2943: goto -> 4330
    //   2946: aload_2
    //   2947: aload_3
    //   2948: invokespecial w : (Lku;)V
    //   2951: goto -> 4330
    //   2954: aload_2
    //   2955: getfield b : Lkq;
    //   2958: aload_3
    //   2959: iconst_1
    //   2960: invokevirtual d : (S)Ljava/lang/String;
    //   2963: invokeinterface s : (Ljava/lang/String;)V
    //   2968: goto -> 4330
    //   2971: aload_2
    //   2972: aload_3
    //   2973: astore_3
    //   2974: astore_2
    //   2975: aload_3
    //   2976: sipush #147
    //   2979: iconst_m1
    //   2980: invokevirtual a : (SB)B
    //   2983: dup
    //   2984: istore #4
    //   2986: tableswitch default -> 3184, 0 -> 3012, 1 -> 3061, 2 -> 3124
    //   3012: aload_2
    //   3013: getfield b : Lkq;
    //   3016: aload_3
    //   3017: sipush #162
    //   3020: invokevirtual d : (S)Ljava/lang/String;
    //   3023: aload_3
    //   3024: sipush #161
    //   3027: invokevirtual c : (S)[B
    //   3030: ifnull -> 3037
    //   3033: iconst_1
    //   3034: goto -> 3038
    //   3037: iconst_0
    //   3038: aload_3
    //   3039: sipush #163
    //   3042: invokevirtual c : (S)[B
    //   3045: ifnull -> 3052
    //   3048: iconst_1
    //   3049: goto -> 3053
    //   3052: iconst_0
    //   3053: invokeinterface a : (Ljava/lang/String;ZZ)V
    //   3058: goto -> 4330
    //   3061: aload_2
    //   3062: getfield b : Lkq;
    //   3065: aload_3
    //   3066: sipush #162
    //   3069: invokevirtual d : (S)Ljava/lang/String;
    //   3072: aload_3
    //   3073: bipush #101
    //   3075: invokevirtual c : (S)[B
    //   3078: ifnull -> 3085
    //   3081: iconst_1
    //   3082: goto -> 3086
    //   3085: iconst_0
    //   3086: aload_3
    //   3087: sipush #161
    //   3090: invokevirtual c : (S)[B
    //   3093: ifnull -> 3100
    //   3096: iconst_1
    //   3097: goto -> 3101
    //   3100: iconst_0
    //   3101: aload_3
    //   3102: sipush #163
    //   3105: invokevirtual c : (S)[B
    //   3108: ifnull -> 3115
    //   3111: iconst_1
    //   3112: goto -> 3116
    //   3115: iconst_0
    //   3116: invokeinterface a : (Ljava/lang/String;ZZZ)V
    //   3121: goto -> 4330
    //   3124: aload_2
    //   3125: getfield b : Lkq;
    //   3128: aload_3
    //   3129: sipush #162
    //   3132: invokevirtual d : (S)Ljava/lang/String;
    //   3135: aload_3
    //   3136: bipush #101
    //   3138: invokevirtual c : (S)[B
    //   3141: ifnull -> 3148
    //   3144: iconst_1
    //   3145: goto -> 3149
    //   3148: iconst_0
    //   3149: aload_3
    //   3150: sipush #161
    //   3153: invokevirtual c : (S)[B
    //   3156: ifnull -> 3163
    //   3159: iconst_1
    //   3160: goto -> 3164
    //   3163: iconst_0
    //   3164: aload_3
    //   3165: sipush #163
    //   3168: invokevirtual c : (S)[B
    //   3171: ifnull -> 3178
    //   3174: iconst_1
    //   3175: goto -> 3179
    //   3178: iconst_0
    //   3179: invokeinterface b : (Ljava/lang/String;ZZZ)V
    //   3184: goto -> 4330
    //   3187: aload_2
    //   3188: aload_3
    //   3189: invokespecial i : (Lku;)V
    //   3192: goto -> 4330
    //   3195: aload_2
    //   3196: aload_3
    //   3197: astore_3
    //   3198: astore_2
    //   3199: aload_3
    //   3200: sipush #192
    //   3203: invokevirtual d : (S)Ljava/lang/String;
    //   3206: astore #4
    //   3208: aload_3
    //   3209: iconst_1
    //   3210: invokevirtual d : (S)Ljava/lang/String;
    //   3213: astore #5
    //   3215: aload_3
    //   3216: sipush #157
    //   3219: lconst_0
    //   3220: invokevirtual a : (SJ)J
    //   3223: lstore #23
    //   3225: aload_3
    //   3226: sipush #194
    //   3229: iconst_0
    //   3230: invokevirtual c : (SI)I
    //   3233: istore #25
    //   3235: new java/lang/StringBuffer
    //   3238: dup
    //   3239: ldc '[processJoinRoom]  '
    //   3241: invokespecial <init> : (Ljava/lang/String;)V
    //   3244: aload #5
    //   3246: invokevirtual append : (Ljava/lang/String;)Ljava/lang/StringBuffer;
    //   3249: ldc ':  '
    //   3251: invokevirtual append : (Ljava/lang/String;)Ljava/lang/StringBuffer;
    //   3254: lload #23
    //   3256: invokevirtual append : (J)Ljava/lang/StringBuffer;
    //   3259: invokevirtual toString : ()Ljava/lang/String;
    //   3262: invokestatic a : (Ljava/lang/String;)V
    //   3265: aload_2
    //   3266: getfield b : Lkq;
    //   3269: aload #4
    //   3271: aload #5
    //   3273: lload #23
    //   3275: iload #25
    //   3277: invokeinterface a : (Ljava/lang/String;Ljava/lang/String;JI)V
    //   3282: goto -> 4330
    //   3285: aload_2
    //   3286: aload_3
    //   3287: astore_3
    //   3288: astore_2
    //   3289: aload_3
    //   3290: sipush #176
    //   3293: invokevirtual c : (S)[B
    //   3296: astore #4
    //   3298: aload_3
    //   3299: iconst_2
    //   3300: invokevirtual c : (S)[B
    //   3303: astore #5
    //   3305: aload_2
    //   3306: getfield b : Lkq;
    //   3309: aload #4
    //   3311: aload #5
    //   3313: invokeinterface a : ([B[B)V
    //   3318: goto -> 4330
    //   3321: aload_2
    //   3322: aload_3
    //   3323: astore_3
    //   3324: astore_2
    //   3325: aload_3
    //   3326: iconst_1
    //   3327: invokevirtual d : (S)Ljava/lang/String;
    //   3330: astore #4
    //   3332: aload_2
    //   3333: getfield b : Lkq;
    //   3336: ifnull -> 3350
    //   3339: aload_2
    //   3340: getfield b : Lkq;
    //   3343: aload #4
    //   3345: invokeinterface o : (Ljava/lang/String;)V
    //   3350: goto -> 4330
    //   3353: aload_2
    //   3354: getfield b : Lkq;
    //   3357: ifnull -> 4330
    //   3360: aload_2
    //   3361: getfield b : Lkq;
    //   3364: invokeinterface T : ()V
    //   3369: goto -> 4330
    //   3372: aload_2
    //   3373: aload_3
    //   3374: astore_3
    //   3375: astore_2
    //   3376: aload_3
    //   3377: bipush #114
    //   3379: iconst_0
    //   3380: invokevirtual c : (SI)I
    //   3383: istore #4
    //   3385: aload_3
    //   3386: iconst_1
    //   3387: invokevirtual d : (S)Ljava/lang/String;
    //   3390: astore #5
    //   3392: aload_3
    //   3393: bipush #83
    //   3395: invokevirtual d : (S)Ljava/lang/String;
    //   3398: astore #23
    //   3400: iload #4
    //   3402: ifle -> 3411
    //   3405: iload #4
    //   3407: iconst_1
    //   3408: invokestatic b : (II)V
    //   3411: aload #5
    //   3413: ifnull -> 3427
    //   3416: aload_2
    //   3417: getfield b : Lkq;
    //   3420: aload #5
    //   3422: invokeinterface v : (Ljava/lang/String;)V
    //   3427: aload #23
    //   3429: ifnull -> 3473
    //   3432: aload_3
    //   3433: bipush #83
    //   3435: iconst_0
    //   3436: invokevirtual b : (SI)I
    //   3439: istore #24
    //   3441: aload_3
    //   3442: bipush #83
    //   3444: iload #24
    //   3446: invokevirtual a : (SI)I
    //   3449: istore #25
    //   3451: aload_3
    //   3452: iload #24
    //   3454: iload #25
    //   3456: iconst_1
    //   3457: invokestatic a : (Lku;IIZ)Lll;
    //   3460: astore #26
    //   3462: aload_2
    //   3463: getfield b : Lkq;
    //   3466: aload #26
    //   3468: invokeinterface c : (Lll;)V
    //   3473: aload_3
    //   3474: iconst_1
    //   3475: invokestatic a : (Lku;I)[Llm;
    //   3478: dup
    //   3479: astore #24
    //   3481: arraylength
    //   3482: ifle -> 3496
    //   3485: aload_2
    //   3486: getfield b : Lkq;
    //   3489: aload #24
    //   3491: invokeinterface a : ([Llm;)V
    //   3496: goto -> 4330
    //   3499: aload_2
    //   3500: aload_3
    //   3501: astore_3
    //   3502: astore_2
    //   3503: aload_3
    //   3504: bipush #114
    //   3506: iconst_m1
    //   3507: invokevirtual c : (SI)I
    //   3510: istore #4
    //   3512: aload_3
    //   3513: bipush #106
    //   3515: iconst_0
    //   3516: invokevirtual c : (SI)I
    //   3519: istore #5
    //   3521: aload_2
    //   3522: getfield b : Lkq;
    //   3525: iload #4
    //   3527: iload #5
    //   3529: invokeinterface f : (II)V
    //   3534: goto -> 4330
    //   3537: aload_2
    //   3538: aload_3
    //   3539: astore_3
    //   3540: astore_2
    //   3541: aload_3
    //   3542: sipush #186
    //   3545: invokevirtual d : (S)Ljava/lang/String;
    //   3548: astore #4
    //   3550: aload_3
    //   3551: iconst_1
    //   3552: invokevirtual d : (S)Ljava/lang/String;
    //   3555: astore #5
    //   3557: invokestatic b : ()Z
    //   3560: ifeq -> 3593
    //   3563: new java/lang/StringBuffer
    //   3566: dup
    //   3567: ldc '[processRequestUpgradeEquipment]  session  '
    //   3569: invokespecial <init> : (Ljava/lang/String;)V
    //   3572: aload #4
    //   3574: invokevirtual append : (Ljava/lang/String;)Ljava/lang/StringBuffer;
    //   3577: ldc '  message  '
    //   3579: invokevirtual append : (Ljava/lang/String;)Ljava/lang/StringBuffer;
    //   3582: aload #5
    //   3584: invokevirtual append : (Ljava/lang/String;)Ljava/lang/StringBuffer;
    //   3587: invokevirtual toString : ()Ljava/lang/String;
    //   3590: invokestatic a : (Ljava/lang/String;)V
    //   3593: aload_2
    //   3594: getfield b : Lkq;
    //   3597: ifnull -> 3613
    //   3600: aload_2
    //   3601: getfield b : Lkq;
    //   3604: aload #4
    //   3606: aload #5
    //   3608: invokeinterface e : (Ljava/lang/String;Ljava/lang/String;)V
    //   3613: goto -> 4330
    //   3616: aload_2
    //   3617: aload_3
    //   3618: astore_3
    //   3619: astore_2
    //   3620: aload_3
    //   3621: sipush #186
    //   3624: invokevirtual d : (S)Ljava/lang/String;
    //   3627: pop
    //   3628: aload_3
    //   3629: sipush #187
    //   3632: iconst_0
    //   3633: invokevirtual a : (SB)B
    //   3636: istore #5
    //   3638: aload_3
    //   3639: bipush #83
    //   3641: invokevirtual d : (S)Ljava/lang/String;
    //   3644: astore #23
    //   3646: aload_3
    //   3647: bipush #114
    //   3649: iconst_m1
    //   3650: invokevirtual c : (SI)I
    //   3653: istore #24
    //   3655: aload_3
    //   3656: bipush #106
    //   3658: iconst_m1
    //   3659: invokevirtual c : (SI)I
    //   3662: istore #25
    //   3664: aload_3
    //   3665: sipush #132
    //   3668: lconst_0
    //   3669: invokevirtual a : (SJ)J
    //   3672: lstore #26
    //   3674: aload_3
    //   3675: iconst_1
    //   3676: invokevirtual d : (S)Ljava/lang/String;
    //   3679: astore #6
    //   3681: aload_3
    //   3682: sipush #188
    //   3685: iconst_0
    //   3686: invokevirtual a : (SB)B
    //   3689: istore #4
    //   3691: aload #23
    //   3693: ifnull -> 3738
    //   3696: iload #5
    //   3698: ifne -> 3721
    //   3701: aload_2
    //   3702: getfield b : Lkq;
    //   3705: aload #23
    //   3707: aload #6
    //   3709: iload #4
    //   3711: lload #26
    //   3713: invokeinterface a : (Ljava/lang/String;Ljava/lang/String;BJ)V
    //   3718: goto -> 3738
    //   3721: aload_2
    //   3722: getfield b : Lkq;
    //   3725: aload #23
    //   3727: aload #6
    //   3729: iload #4
    //   3731: lload #26
    //   3733: invokeinterface b : (Ljava/lang/String;Ljava/lang/String;BJ)V
    //   3738: iload #24
    //   3740: ifle -> 3785
    //   3743: iload #5
    //   3745: ifne -> 3766
    //   3748: aload_2
    //   3749: getfield b : Lkq;
    //   3752: aload #6
    //   3754: iload #4
    //   3756: lload #26
    //   3758: invokeinterface a : (Ljava/lang/String;BJ)V
    //   3763: goto -> 4330
    //   3766: aload_2
    //   3767: getfield b : Lkq;
    //   3770: iload #24
    //   3772: iload #25
    //   3774: aload #6
    //   3776: iload #4
    //   3778: lload #26
    //   3780: invokeinterface a : (IILjava/lang/String;BJ)V
    //   3785: goto -> 4330
    //   3788: aload_2
    //   3789: aload_3
    //   3790: invokespecial A : (Lku;)V
    //   3793: goto -> 4330
    //   3796: aload_2
    //   3797: aload_3
    //   3798: astore_3
    //   3799: astore_2
    //   3800: aload_3
    //   3801: sipush #186
    //   3804: invokevirtual d : (S)Ljava/lang/String;
    //   3807: astore #4
    //   3809: aload_3
    //   3810: bipush #83
    //   3812: invokevirtual d : (S)Ljava/lang/String;
    //   3815: astore #5
    //   3817: aload_3
    //   3818: iconst_1
    //   3819: invokevirtual d : (S)Ljava/lang/String;
    //   3822: astore #23
    //   3824: invokestatic b : ()Z
    //   3827: ifeq -> 3860
    //   3830: new java/lang/StringBuffer
    //   3833: dup
    //   3834: ldc '[processRequestUpgradeEquipment]  equipKey  '
    //   3836: invokespecial <init> : (Ljava/lang/String;)V
    //   3839: aload #5
    //   3841: invokevirtual append : (Ljava/lang/String;)Ljava/lang/StringBuffer;
    //   3844: ldc ' message'
    //   3846: invokevirtual append : (Ljava/lang/String;)Ljava/lang/StringBuffer;
    //   3849: aload #23
    //   3851: invokevirtual append : (Ljava/lang/String;)Ljava/lang/StringBuffer;
    //   3854: invokevirtual toString : ()Ljava/lang/String;
    //   3857: invokestatic a : (Ljava/lang/String;)V
    //   3860: aload_2
    //   3861: getfield b : Lkq;
    //   3864: ifnull -> 3882
    //   3867: aload_2
    //   3868: getfield b : Lkq;
    //   3871: aload #4
    //   3873: aload #5
    //   3875: aload #23
    //   3877: invokeinterface a : (Ljava/lang/String;Ljava/lang/String;Ljava/lang/String;)V
    //   3882: goto -> 4330
    //   3885: aload_2
    //   3886: aload_3
    //   3887: astore_3
    //   3888: astore_2
    //   3889: aload_3
    //   3890: sipush #186
    //   3893: invokevirtual d : (S)Ljava/lang/String;
    //   3896: pop
    //   3897: aload_3
    //   3898: sipush #187
    //   3901: iconst_0
    //   3902: invokevirtual a : (SB)B
    //   3905: istore #5
    //   3907: aload_3
    //   3908: bipush #83
    //   3910: invokevirtual d : (S)Ljava/lang/String;
    //   3913: astore #23
    //   3915: aload_3
    //   3916: bipush #114
    //   3918: iconst_m1
    //   3919: invokevirtual c : (SI)I
    //   3922: istore #24
    //   3924: aload_3
    //   3925: bipush #106
    //   3927: iconst_m1
    //   3928: invokevirtual c : (SI)I
    //   3931: istore #25
    //   3933: aload_3
    //   3934: sipush #132
    //   3937: lconst_0
    //   3938: invokevirtual a : (SJ)J
    //   3941: lstore #26
    //   3943: aload_3
    //   3944: iconst_1
    //   3945: invokevirtual d : (S)Ljava/lang/String;
    //   3948: astore #6
    //   3950: aload_3
    //   3951: sipush #188
    //   3954: iconst_0
    //   3955: invokevirtual a : (SB)B
    //   3958: istore #4
    //   3960: invokestatic b : ()Z
    //   3963: ifeq -> 3986
    //   3966: new java/lang/StringBuffer
    //   3969: dup
    //   3970: ldc '[processModifiedUpgradeEquipment]readyStatus   '
    //   3972: invokespecial <init> : (Ljava/lang/String;)V
    //   3975: iload #4
    //   3977: invokevirtual append : (I)Ljava/lang/StringBuffer;
    //   3980: invokevirtual toString : ()Ljava/lang/String;
    //   3983: invokestatic a : (Ljava/lang/String;)V
    //   3986: aload #23
    //   3988: ifnull -> 4033
    //   3991: iload #5
    //   3993: ifne -> 4016
    //   3996: aload_2
    //   3997: getfield b : Lkq;
    //   4000: aload #23
    //   4002: aload #6
    //   4004: iload #4
    //   4006: lload #26
    //   4008: invokeinterface d : (Ljava/lang/String;Ljava/lang/String;BJ)V
    //   4013: goto -> 4033
    //   4016: aload_2
    //   4017: getfield b : Lkq;
    //   4020: aload #23
    //   4022: aload #6
    //   4024: iload #4
    //   4026: lload #26
    //   4028: invokeinterface c : (Ljava/lang/String;Ljava/lang/String;BJ)V
    //   4033: iload #24
    //   4035: ifle -> 4080
    //   4038: iload #5
    //   4040: ifne -> 4061
    //   4043: aload_2
    //   4044: getfield b : Lkq;
    //   4047: aload #6
    //   4049: iload #4
    //   4051: lload #26
    //   4053: invokeinterface b : (Ljava/lang/String;BJ)V
    //   4058: goto -> 4330
    //   4061: aload_2
    //   4062: getfield b : Lkq;
    //   4065: iload #24
    //   4067: iload #25
    //   4069: aload #6
    //   4071: iload #4
    //   4073: lload #26
    //   4075: invokeinterface b : (IILjava/lang/String;BJ)V
    //   4080: goto -> 4330
    //   4083: aload_2
    //   4084: aload_3
    //   4085: invokespecial B : (Lku;)V
    //   4088: goto -> 4330
    //   4091: aload_2
    //   4092: aload_3
    //   4093: astore_3
    //   4094: astore_2
    //   4095: aload_3
    //   4096: bipush #83
    //   4098: invokevirtual d : (S)Ljava/lang/String;
    //   4101: dup
    //   4102: astore #4
    //   4104: ifnull -> 4138
    //   4107: aload_3
    //   4108: sipush #175
    //   4111: invokevirtual d : (S)Ljava/lang/String;
    //   4114: pop
    //   4115: aload_3
    //   4116: sipush #157
    //   4119: lconst_0
    //   4120: invokevirtual a : (SJ)J
    //   4123: lstore #23
    //   4125: aload_2
    //   4126: getfield b : Lkq;
    //   4129: aload #4
    //   4131: lload #23
    //   4133: invokeinterface a : (Ljava/lang/String;J)V
    //   4138: aload_3
    //   4139: bipush #114
    //   4141: iconst_0
    //   4142: invokevirtual c : (SI)I
    //   4145: dup
    //   4146: istore #5
    //   4148: ifle -> 4190
    //   4151: aload_3
    //   4152: sipush #175
    //   4155: invokevirtual d : (S)Ljava/lang/String;
    //   4158: pop
    //   4159: aload_3
    //   4160: bipush #106
    //   4162: iconst_0
    //   4163: invokevirtual c : (SI)I
    //   4166: istore #24
    //   4168: aload_3
    //   4169: sipush #157
    //   4172: lconst_0
    //   4173: invokevirtual a : (SJ)J
    //   4176: pop2
    //   4177: aload_2
    //   4178: getfield b : Lkq;
    //   4181: iload #5
    //   4183: iload #24
    //   4185: invokeinterface g : (II)V
    //   4190: goto -> 4330
    //   4193: aload_2
    //   4194: aload_3
    //   4195: invokespecial y : (Lku;)V
    //   4198: goto -> 4330
    //   4201: aload_2
    //   4202: aload_3
    //   4203: invokespecial x : (Lku;)V
    //   4206: goto -> 4330
    //   4209: aload_2
    //   4210: aload_3
    //   4211: astore_3
    //   4212: astore_2
    //   4213: aload_3
    //   4214: sipush #152
    //   4217: iconst_m1
    //   4218: invokevirtual a : (SB)B
    //   4221: istore #4
    //   4223: aload_3
    //   4224: bipush #106
    //   4226: iconst_0
    //   4227: invokevirtual c : (SI)I
    //   4230: istore #5
    //   4232: new java/lang/StringBuffer
    //   4235: dup
    //   4236: ldc '[processListMarketProducts]catid == '
    //   4238: invokespecial <init> : (Ljava/lang/String;)V
    //   4241: iload #4
    //   4243: invokevirtual append : (I)Ljava/lang/StringBuffer;
    //   4246: ldc 'qty =='
    //   4248: invokevirtual append : (Ljava/lang/String;)Ljava/lang/StringBuffer;
    //   4251: iload #5
    //   4253: invokevirtual append : (I)Ljava/lang/StringBuffer;
    //   4256: invokevirtual toString : ()Ljava/lang/String;
    //   4259: invokestatic a : (Ljava/lang/String;)V
    //   4262: aload_2
    //   4263: getfield b : Lkq;
    //   4266: iload #4
    //   4268: iload #5
    //   4270: aload_2
    //   4271: aload_3
    //   4272: invokespecial u : (Lku;)[Llq;
    //   4275: invokeinterface a : (II[Llq;)V
    //   4280: goto -> 4330
    //   4283: aload_2
    //   4284: aload_3
    //   4285: invokespecial z : (Lku;)V
    //   4288: goto -> 4330
    //   4291: aload_2
    //   4292: aload_3
    //   4293: invokespecial D : (Lku;)V
    //   4296: goto -> 4330
    //   4299: aload_2
    //   4300: aload_3
    //   4301: astore_3
    //   4302: astore_2
    //   4303: aload_3
    //   4304: iconst_1
    //   4305: invokevirtual d : (S)Ljava/lang/String;
    //   4308: astore #4
    //   4310: aload_2
    //   4311: getfield b : Lkq;
    //   4314: aload #4
    //   4316: invokeinterface w : (Ljava/lang/String;)V
    //   4321: goto -> 4330
    //   4324: dup
    //   4325: astore #4
    //   4327: invokevirtual printStackTrace : ()V
    //   4330: aload_0
    //   4331: getfield f : Z
    //   4334: ifeq -> 11
    //   4337: return
    // Exception table:
    //   from	to	target	type
    //   11	329	332	java/lang/Throwable
    //   313	319	322	java/lang/Throwable
    //   352	358	361	java/lang/Throwable
    //   397	2343	4324	java/lang/Throwable
    //   2346	4321	4324	java/lang/Throwable
  }
  
  private lh a(ku paramku, int paramInt1, int paramInt2) {
    paramInt1 = paramku.a((short)15, 0, -1, (byte)-1);
    lh lh;
    (lh = new lh(paramInt1)).b = paramku.b(0);
    lh.c = paramku.d((short)26, 0, -1);
    lh.f = paramku.a((short)16, 0, -1, (byte)0);
    lh.g = paramku.a((short)15, 0, -1, (byte)0);
    lh.G = paramku.a((short)27, 0, -1, 0);
    lh.e = paramku.a((short)24, 0, -1, (byte)0);
    lh.H = paramku.a((short)43, 0, -1, 0);
    lh.s = paramku.a((short)17, 0, -1, 0);
    lh.r = paramku.a((short)47, 0, -1, 1);
    lh.u = paramku.a((short)18, 0, -1, 0);
    lh.t = paramku.a((short)48, 0, -1, 1);
    lh.w = paramku.a((short)45, 0, -1, 0);
    lh.v = paramku.a((short)49, 0, -1, 1);
    lh.S = paramku.d((short)209);
    lh.R = paramku.d((short)210);
    if (lh.Q == null)
      if (lh.G > 100 && lh.G <= 200) {
        lh.Q = "i Hip";
      } else if (lh.G > 200) {
        lh.Q = "Chin Vng";
      } else {
        lh.Q = "Ho Kit";
      }  
    lh.ab = paramku.c((short)160, 0);
    paramInt2 = paramku.a((short)64, 0, -1);
    lh.E = new lv[paramInt2];
    if (paramInt2 > 0) {
      int k = paramku.b((short)64, 0, -1);
      for (byte b1 = 0; b1 < paramInt2; b1++) {
        int m = paramku.a((short)64, k);
        lh.E[b1] = new lv(paramku.a(k, -1));
        k = m;
      } 
    } 
    lh.D = new ll[paramku.a((short)83, 0, -1)];
    int i = paramku.a((short)83, 0);
    int j;
    for (j = 0; j < lh.D.length; j++) {
      int k = paramku.a((short)83, i);
      lh.D[j] = a(paramku, i, k, false);
      i = k;
    } 
    j = paramku.a((short)90, 0, -1);
    i = paramku.a((short)90, 0);
    for (byte b = 0; b < j; b++) {
      paramInt2 = paramku.a((short)90, i);
      int m = paramku.a(i, 0);
      byte b1 = paramku.a((short)91, i, paramInt2, (byte)0);
      df df = new df(m);
      int n = paramku.a((short)93, i, paramInt2, 0);
      byte[] arrayOfByte2 = paramku.c((short)95, i, paramInt2);
      df.d = new dg(n, arrayOfByte2);
      df.f = new dg[] { df.d };
      n = paramku.a((short)96, i, paramInt2, 0);
      byte[] arrayOfByte1 = paramku.c((short)98, i, paramInt2);
      df.e = new dg(n, arrayOfByte1);
      switch (b1) {
        case 0:
          lh.U = df;
          break;
        case 1:
          lh.V = df;
          break;
        case 2:
          lh.W = df;
          break;
      } 
      int k = paramInt2;
    } 
    return lh;
  }
  
  private lh b(ku paramku, int paramInt1, int paramInt2) {
    try {
      byte b = paramku.a((short)15, paramInt1, paramInt2, (byte)-1);
      lh lh;
      (lh = new lh(b)).b = paramku.b(paramInt1);
      lh.c = paramku.d((short)26, paramInt1, paramInt2);
      lh.O = (paramku.c((short)36, paramInt1, paramInt2) != null);
      lh.f = paramku.a((short)16, paramInt1, paramInt2, (byte)0);
      lh.g = paramku.a((short)15, paramInt1, paramInt2, (byte)0);
      lh.G = paramku.a((short)27, paramInt1, paramInt2, 0);
      lh.Y = paramku.a((short)4, paramInt1, paramInt2, 0);
      lh.T = paramku.a((short)19, paramInt1, paramInt2, (byte)0);
      lh.s = paramku.a((short)17, paramInt1, paramInt2, 0);
      lh.r = paramku.a((short)47, paramInt1, paramInt2, 1);
      lh.u = paramku.a((short)18, paramInt1, paramInt2, 0);
      lh.t = paramku.a((short)48, paramInt1, paramInt2, 1);
      lh.w = paramku.a((short)45, paramInt1, paramInt2, 0);
      lh.v = paramku.a((short)49, paramInt1, paramInt2, 1);
      lh.S = paramku.d((short)209);
      lh.R = paramku.d((short)210);
      if (lh.Q == null)
        if (lh.G > 100 && lh.G <= 200) {
          lh.Q = "i Hip";
        } else if (lh.G > 200) {
          lh.Q = "Chin Vng";
        } else {
          lh.Q = "Ho Kit";
        }  
      int i = paramku.a((short)64, paramInt1, paramInt2);
      lh.E = new lv[i];
      if (i > 0) {
        int n = paramku.b((short)64, paramInt1, paramInt2);
        for (byte b2 = 0; b2 < i; b2++) {
          int i1 = paramku.a((short)64, n);
          lh.E[b2] = new lv(paramku.a(n, -1));
          (lh.E[b2]).b = paramku.d((short)26, n, i1);
          (lh.E[b2]).d = paramku.d((short)66, n, i1);
          (lh.E[b2]).f = paramku.a((short)67, n, i1, -1);
          (lh.E[b2]).e = paramku.a((short)68, n, i1, -1);
          int i2 = paramku.a((short)69, n, i1);
          (lh.E[b2]).h = new String[i2];
          int i3 = paramku.b((short)69, n, i1);
          for (byte b3 = 0; b3 < i2; b3++) {
            int i4 = paramku.a((short)69, i3);
            (lh.E[b2]).h[b3] = paramku.b(i3);
            i3 = i4;
          } 
          n = i1;
        } 
      } 
      lh.D = new ll[paramku.a((short)83, paramInt1, paramInt2)];
      int k = paramku.a((short)83, paramInt1);
      int m;
      for (m = 0; m < lh.D.length; m++) {
        int n = paramku.a((short)83, k);
        lh.D[m] = a(paramku, k, n, false);
        k = n;
      } 
      ku ku1 = paramku;
      ky ky1 = this;
      lh.F = a(ku1, 0);
      m = paramku.a((short)90, paramInt1, paramInt2);
      int j = paramku.a((short)90, paramInt1);
      for (byte b1 = 0; b1 < m; b1++) {
        int n = paramku.a((short)90, j);
        int i1 = paramku.a(j, 0);
        byte b2 = paramku.a((short)91, j, n, (byte)0);
        df df = new df(i1);
        paramInt1 = paramku.a((short)93, j, n, 0);
        byte[] arrayOfByte = paramku.c((short)95, j, n);
        df.d = new dg(paramInt1, arrayOfByte);
        df.f = new dg[] { df.d };
        paramInt1 = paramku.a((short)96, j, n, 0);
        arrayOfByte = paramku.c((short)98, j, n);
        df.e = new dg(paramInt1, arrayOfByte);
        switch (b2) {
          case 0:
            lh.U = df;
            break;
          case 1:
            lh.V = df;
            break;
          case 2:
            lh.W = df;
            break;
        } 
        j = n;
      } 
      return lh;
    } catch (Exception exception2) {
      Exception exception1;
      (exception1 = null).printStackTrace();
      MGMIDlet mGMIDlet;
      (mGMIDlet = MGMIDlet.d()).notifyDestroyed();
      return null;
    } 
  }
  
  private lh c(ku paramku, int paramInt1, int paramInt2) {
    try {
      lh lh;
      (lh = new lh(0)).b = paramku.b(paramInt1);
      lh.c = paramku.d((short)26, paramInt1, paramInt2);
      lh.O = (paramku.c((short)36, paramInt1, paramInt2) != null);
      lh.f = paramku.a((short)16, paramInt1, paramInt2, (byte)0);
      lh.g = paramku.a((short)15, paramInt1, paramInt2, (byte)0);
      lh.G = paramku.a((short)27, paramInt1, paramInt2, 0);
      lh.Y = paramku.a((short)4, paramInt1, paramInt2, 0);
      lh.T = paramku.a((short)19, paramInt1, paramInt2, (byte)0);
      lh.s = paramku.a((short)17, paramInt1, paramInt2, 0);
      lh.r = paramku.a((short)47, paramInt1, paramInt2, 1);
      lh.u = paramku.a((short)18, paramInt1, paramInt2, 0);
      lh.t = paramku.a((short)48, paramInt1, paramInt2, 1);
      lh.w = paramku.a((short)45, paramInt1, paramInt2, 0);
      lh.v = paramku.a((short)49, paramInt1, paramInt2, 1);
      lh.S = paramku.d((short)209);
      lh.R = paramku.d((short)210);
      if (lh.Q == null)
        if (lh.G > 100 && lh.G <= 200) {
          lh.Q = "i Hip";
        } else if (lh.G > 200) {
          lh.Q = "Chin Vng";
        } else {
          lh.Q = "Ho Kit";
        }  
      int i = paramku.a((short)64, paramInt1, paramInt2);
      lh.E = new lv[i];
      if (i > 0) {
        int m = paramku.b((short)64, paramInt1, paramInt2);
        for (byte b1 = 0; b1 < i; b1++) {
          int n = paramku.a((short)64, m);
          lh.E[b1] = new lv(paramku.a(m, -1));
          m = n;
        } 
      } 
      lh.D = new ll[paramku.a((short)83, paramInt1, paramInt2)];
      int j = paramku.a((short)83, paramInt1);
      int k;
      for (k = 0; k < lh.D.length; k++) {
        int m = paramku.a((short)83, j);
        lh.D[k] = a(paramku, j, m, false);
        j = m;
      } 
      lh.F = new lm[paramku.a((short)114, paramInt1, paramInt2)];
      j = paramku.a((short)114, paramInt1);
      for (k = 0; k < lh.F.length; k++) {
        int m = paramku.a((short)114, j);
        i = paramku.a(j, 0);
        lh.F[k] = new lm(i);
        (lh.F[k]).g = paramku.a((short)106, j, m, 0);
        (lh.F[k]).j = paramku.a((short)4, j, m, 0);
        j = m;
      } 
      k = paramku.a((short)90, paramInt1, paramInt2);
      j = paramku.a((short)90, paramInt1);
      for (byte b = 0; b < k; b++) {
        i = paramku.a((short)90, j);
        paramInt1 = paramku.a(j, 0);
        paramInt2 = paramku.a((short)91, j, i, (byte)0);
        df df = new df(paramInt1);
        int n = paramku.a((short)93, j, i, 0);
        byte[] arrayOfByte2 = paramku.c((short)95, j, i);
        df.d = new dg(n, arrayOfByte2);
        df.f = new dg[] { df.d };
        n = paramku.a((short)96, j, i, 0);
        byte[] arrayOfByte1 = paramku.c((short)98, j, i);
        df.e = new dg(n, arrayOfByte1);
        switch (paramInt2) {
          case 0:
            lh.U = df;
            break;
          case 1:
            lh.V = df;
            break;
          case 2:
            lh.W = df;
            break;
        } 
        int m = i;
      } 
      return lh;
    } catch (Exception exception2) {
      Exception exception1;
      (exception1 = null).printStackTrace();
      MGMIDlet mGMIDlet;
      (mGMIDlet = MGMIDlet.d()).notifyDestroyed();
      return null;
    } 
  }
  
  private lh a(ku paramku) {
    byte b = paramku.a((short)15, 0, -1, (byte)-1);
    lh lh;
    (lh = new lh(b)).b = paramku.d((short)9);
    lh.c = paramku.d((short)26);
    lh.g = paramku.a((short)15, (byte)0);
    lh.f = paramku.a((short)16, (byte)0);
    lh.G = paramku.c((short)27, 0);
    lh.s = paramku.c((short)17, 0);
    lh.r = paramku.c((short)47, 0);
    lh.u = paramku.c((short)18, 0);
    lh.t = paramku.c((short)48, 0);
    lh.h = paramku.c((short)118, 0);
    lh.j = paramku.c((short)119, 0);
    lh.i = paramku.c((short)120, 0);
    lh.k = paramku.c((short)121, 0);
    lh.l = paramku.c((short)196, 0);
    lh.m = paramku.c((short)197, 0);
    lh.n = paramku.c((short)198, 0);
    lh.o = paramku.c((short)199, 0);
    lh.p = paramku.c((short)116, 0);
    lh.q = paramku.c((short)115, 0);
    ct.a("[readFighterInf] addHealth " + lh.p + " heatlPec  " + lh.q);
    lh.J = paramku.c((short)42, 0);
    lh.H = paramku.c((short)43, 0);
    lh.I = paramku.c((short)99, 10000);
    lh.K = paramku.c((short)53, 0);
    lh.L = paramku.c((short)76, 0);
    lh.M = paramku.c((short)73, 0);
    lh.N = paramku.c((short)74, 0);
    lh.S = paramku.d((short)209);
    lh.R = paramku.d((short)210);
    if (lh.Q == null)
      if (lh.G > 100 && lh.G <= 200) {
        lh.Q = "i Hip";
      } else if (lh.G > 200) {
        lh.Q = "Chin Vng";
      } else {
        lh.Q = "Ho Kit";
      }  
    lh.ab = paramku.c((short)160, 0);
    lh.Z = (paramku.a((short)165, (byte)0) == 1);
    lh.aa = (paramku.a((short)166, (byte)0) == 1);
    int i = paramku.b((short)64);
    lh.E = new lv[i];
    if (i > 0) {
      int n = paramku.a((short)64, 0);
      for (byte b2 = 0; b2 < i; b2++) {
        int i1 = paramku.a((short)64, n);
        lh.E[b2] = new lv(paramku.a(n, -1));
        (lh.E[b2]).f = paramku.a((short)67, n, i1, -1);
        (lh.E[b2]).e = paramku.a((short)68, n, i1, -1);
        paramku.a((short)89, n, i1, (byte)-1);
        n = i1;
      } 
    } 
    lh.D = new ll[paramku.b((short)83)];
    int j = paramku.b((short)83, 0);
    int k;
    for (k = 0; k < lh.D.length; k++) {
      int n = paramku.a((short)83, j);
      lh.D[k] = a(paramku, j, n, false);
      j = n;
    } 
    lh.F = k(paramku);
    k = paramku.b((short)90);
    j = paramku.b((short)90, 0);
    int m;
    for (m = 0; m < k; m++) {
      i = paramku.a((short)90, j);
      int i1 = paramku.a(j, 0);
      byte b2 = paramku.a((short)91, j, i, (byte)0);
      df df = new df(i1);
      int i2 = paramku.a((short)93, j, i, 0);
      byte[] arrayOfByte2 = paramku.c((short)95, j, i);
      df.d = new dg(i2, arrayOfByte2);
      df.f = new dg[] { df.d };
      i2 = paramku.a((short)96, j, i, 0);
      byte[] arrayOfByte1 = paramku.c((short)98, j, i);
      df.e = new dg(i2, arrayOfByte1);
      switch (b2) {
        case 0:
          lh.U = df;
          break;
        case 1:
          lh.V = df;
          break;
        case 2:
          lh.W = df;
          break;
      } 
      int n = i;
    } 
    lt[] arrayOfLt = new lt[m = paramku.b((short)158)];
    j = paramku.b((short)158, 0);
    for (byte b1 = 0; b1 < m; b1++) {
      int n = paramku.a((short)158, j);
      arrayOfLt[b1] = new lt();
      paramku.d((short)158, j, n);
      (arrayOfLt[b1]).a = paramku.a((short)4, j, n, 0);
      (arrayOfLt[b1]).b = paramku.a((short)157, j, n, 0L);
      j = n;
    } 
    lh.ac = arrayOfLt;
    return lh;
  }
  
  private void b(ku paramku) {
    int i = paramku.c((short)23, 0);
    String str = paramku.d((short)9);
    if ((i & 0x1) != 0) {
      int j = paramku.b((short)90);
      int k = paramku.b((short)90, 0);
      byte b1 = paramku.a((short)15, (byte)0);
      byte b2 = paramku.a((short)16, (byte)0);
      df df1 = null;
      df df2 = null;
      df df3 = null;
      for (byte b = 0; b < j; b++) {
        int n = paramku.a((short)90, k);
        int i1 = paramku.a(k, 0);
        byte b3 = paramku.a((short)91, k, n, (byte)0);
        df df = new df(i1);
        int i2 = paramku.a((short)93, k, n, 0);
        byte[] arrayOfByte2 = paramku.c((short)95, k, n);
        df.d = new dg(i2, arrayOfByte2);
        df.f = new dg[] { df.d };
        i2 = paramku.a((short)96, k, n, 0);
        byte[] arrayOfByte1 = paramku.c((short)98, k, n);
        df.e = new dg(i2, arrayOfByte1);
        switch (b3) {
          case 0:
            df1 = df;
            break;
          case 1:
            df2 = df;
            break;
          case 2:
            df3 = df;
            break;
        } 
        int m = n;
      } 
      if (this.b != null)
        this.b.a(str, b1, b2, df1, df2, df3); 
    } 
    if ((i & 0x2) != 0) {
      int j = paramku.c((short)27, 0);
      int k = paramku.c((short)118, 0);
      int m = paramku.c((short)119, 0);
      int n = paramku.c((short)120, 0);
      int i1 = paramku.c((short)121, 0);
      int i2 = paramku.c((short)196, 0);
      int i3 = paramku.c((short)197, 0);
      int i4 = paramku.c((short)198, 0);
      int i5 = paramku.c((short)199, 0);
      int i6 = paramku.c((short)116, 0);
      int i7 = paramku.c((short)115, 0);
      if (this.b != null)
        this.b.a(str, j, k, m, n, i1, i2, i3, i4, i5, i6, i7); 
    } 
    if ((i & 0x4) != 0) {
      int j = paramku.c((short)17, 0);
      int k = paramku.c((short)47, 0);
      int m = paramku.c((short)42, 0);
      int n = paramku.c((short)73, 0);
      int i1 = paramku.c((short)74, 0);
      int i2 = paramku.c((short)43, 0);
      int i3 = paramku.c((short)99, 10000);
      if (this.b != null)
        this.b.a(str, j, k, m, n, i1, i2, i3); 
    } 
    if ((i & 0x8) != 0) {
      String str3;
      int j = paramku.c((short)53, 0);
      int k = paramku.c((short)76, 0);
      int m = paramku.c((short)160, 0);
      int n = paramku.c((short)27, 0);
      String str1 = paramku.d((short)209);
      String str2 = paramku.d((short)210);
      if (n > 100 && n <= 200) {
        str3 = "i Hip";
      } else if (n > 200) {
        str3 = "Chin Vng";
      } else {
        str3 = "Ho Kit";
      } 
      if (this.b != null)
        this.b.a(str, j, k, m, str1, str2, str3); 
    } 
    if ((i & 0x10) != 0) {
      this.b.c((paramku.a((short)165, (byte)0) == 1));
      this.b.d((paramku.a((short)166, (byte)0) == 1));
    } 
    if ((i & 0x20) != 0) {
      int j;
      lv[] arrayOfLv = new lv[j = paramku.b((short)64)];
      if (j > 0) {
        int k = paramku.a((short)64, 0);
        for (byte b = 0; b < j; b++) {
          int m = paramku.a((short)64, k);
          arrayOfLv[b] = new lv(paramku.a(k, -1));
          (arrayOfLv[b]).f = paramku.a((short)67, k, m, -1);
          k = m;
        } 
      } 
      if (this.b != null)
        this.b.a(arrayOfLv); 
    } 
    if ((i & 0x40) != 0) {
      ll[] arrayOfLl = new ll[paramku.b((short)83)];
      int j = paramku.b((short)83, 0);
      for (byte b = 0; b < arrayOfLl.length; b++) {
        int k = paramku.a((short)83, j);
        arrayOfLl[b] = a(paramku, j, k, false);
        j = k;
      } 
      if (this.b != null)
        this.b.a(str, arrayOfLl); 
    } 
    if ((i & 0x100) != 0) {
      int j;
      lt[] arrayOfLt = new lt[j = paramku.b((short)158)];
      int k = paramku.b((short)158, 0);
      for (byte b = 0; b < j; b++) {
        int m = paramku.a((short)158, k);
        arrayOfLt[b] = new lt();
        paramku.d((short)158, k, m);
        (arrayOfLt[b]).a = paramku.a((short)4, k, m, 0);
        (arrayOfLt[b]).b = paramku.a((short)157, k, m, 0L);
        k = m;
      } 
      if (this.b != null)
        this.b.a(arrayOfLt); 
    } 
    if (this.b != null)
      this.b.U(); 
  }
  
  private static ll a(ku paramku, int paramInt1, int paramInt2, boolean paramBoolean) {
    String str = paramku.b(paramInt1);
    byte b = paramku.a((short)84, paramInt1, paramInt2, (byte)0);
    ll ll;
    (ll = new ll(str, b)).n = paramku.a((short)4, paramInt1, paramInt2, 0);
    ll.p = paramku.a((short)139, paramInt1, paramInt2, -1);
    ll.j = paramku.a((short)27, paramInt1, paramInt2, 0);
    if (paramBoolean) {
      ll.d = paramku.d((short)26, paramInt1, paramInt2);
      ll.i = paramku.a((short)135, paramInt1, paramInt2, -1);
      ll.f = paramku.a((short)15, paramInt1, paramInt2, (byte)7);
      ll.h = paramku.a((short)16, paramInt1, paramInt2, (byte)2);
      ll.m = paramku.a((short)138, paramInt1, paramInt2, (byte)0);
      ll.q = paramku.a((short)144, paramInt1, paramInt2, 0);
      ll.g = paramku.d((short)117, paramInt1, paramInt2);
      ll.s = paramku.a((short)156, paramInt1, paramInt2, (byte)-1);
      ll.t = paramku.a((short)85, paramInt1, paramInt2, (byte)1);
      ll.k = paramku.a((short)190, paramInt1, paramInt2, (byte)-1);
      lb lb;
      (lb = new lb()).a = paramku.a((short)118, paramInt1, paramInt2, 0);
      lb.b = paramku.a((short)119, paramInt1, paramInt2, 0);
      lb.c = paramku.a((short)120, paramInt1, paramInt2, 0);
      lb.d = paramku.a((short)121, paramInt1, paramInt2, 0);
      lb.e = paramku.a((short)72, paramInt1, paramInt2, 0);
      lb.f = paramku.a((short)71, paramInt1, paramInt2, 0);
      lb.g = paramku.a((short)126, paramInt1, paramInt2, 0);
      lb.h = paramku.a((short)124, paramInt1, paramInt2, 0);
      lb.i = paramku.a((short)47, paramInt1, paramInt2, 0);
      lb.j = paramku.a((short)200, paramInt1, paramInt2, 0);
      lb.k = paramku.a((short)201, paramInt1, paramInt2, 0);
      lb.l = paramku.a((short)202, paramInt1, paramInt2, 0);
      lb.m = paramku.a((short)203, paramInt1, paramInt2, 0);
      lb.n = paramku.a((short)204, paramInt1, paramInt2, 0);
      lb.o = paramku.a((short)221, paramInt1, paramInt2, 0);
      ll.r = lb;
    } 
    return ll;
  }
  
  private void c(ku paramku) {
    byte b = paramku.a((short)12, (byte)0);
    String str = paramku.d((short)131);
    int i = paramku.c((short)41, -1);
    int j = paramku.c((short)13, 0);
    int[] arrayOfInt = new int[paramku.b((short)4)];
    int k = paramku.b((short)4, 0);
    int m;
    for (m = 0; m < arrayOfInt.length; m++) {
      arrayOfInt[m] = paramku.a(k, 0);
      k++;
    } 
    this.b.a((b == 2), str, i, arrayOfInt, j);
    m = paramku.c((short)170, -1);
    String[] arrayOfString;
    if ((arrayOfString = new String[paramku.b((short)1)]).length > 0) {
      int n = paramku.b((short)1, 0);
      for (i = 0; i < arrayOfString.length; i++) {
        j = paramku.a((short)1, n);
        arrayOfString[i] = paramku.b(n);
        n = j;
      } 
    } 
    this.b.a(m, arrayOfString);
  }
  
  private void d(ku paramku) {
    try {
      byte b = paramku.a((short)12, (byte)0);
      String str = paramku.d((short)20);
      if (b == 0) {
        jm[] arrayOfJm1 = new jm[paramku.b((short)21)];
        int m = paramku.b((short)21, 0);
        byte b2;
        for (b2 = 0; b2 < arrayOfJm1.length; b2++) {
          int n = paramku.a((short)21, m);
          jm jm;
          (jm = new jm()).c = paramku.a(m, -1);
          jm.b = paramku.d((short)26, m, n);
          jm.a = paramku.a((short)22, m, n, (byte)0);
          jm.d = paramku.a((short)102, m, n, 0);
          jm.e = paramku.a((short)103, m, n, 0);
          jm.f = paramku.a((short)104, m, n, 0);
          jm.g = paramku.a((short)105, m, n, 0);
          jm.h = (paramku.a((short)101, m, n, (byte)0) == 1);
          jm.i = paramku.a((short)4, m, n, 0);
          arrayOfJm1[b2] = jm;
          m = n;
        } 
        for (b2 = 0; b2 < arrayOfJm1.length - 1; b2++) {
          for (int n = b2 + 1; n < arrayOfJm1.length; n++) {
            if ((arrayOfJm1[b2]).c > (arrayOfJm1[n]).c) {
              jm jm = arrayOfJm1[b2];
              arrayOfJm1[b2] = arrayOfJm1[n];
              arrayOfJm1[n] = jm;
            } 
          } 
        } 
        this.b.a(str, arrayOfJm1);
        return;
      } 
      a a = new a();
      jn jn;
      (jn = new jn()).a = str;
      jn.b = paramku.d((short)26);
      jn.c = paramku.c((short)41, 0);
      jn.d = paramku.c((short)56, 0);
      jn.e = paramku.c((short)57, 0);
      jn.h = paramku.c((short)55);
      jn.i = paramku.c((short)54);
      jn.j = paramku.c((short)61);
      jn.k = paramku.c((short)60, 0);
      jn.f = paramku.c((short)63, 0);
      jn.g = paramku.c((short)29, 0);
      a.a(new Integer(jn.k));
      a.a(new Integer(jn.f));
      a.a(new Integer(jn.g));
      jm[] arrayOfJm = new jm[paramku.b((short)21)];
      int j = paramku.b((short)21, 0);
      int k;
      for (k = 0; k < arrayOfJm.length; k++) {
        int m = paramku.a((short)21, j);
        jm jm;
        (jm = new jm()).c = paramku.a(j, -1);
        jm.b = paramku.d((short)26, j, m);
        jm.a = paramku.a((short)22, j, m, (byte)0);
        jm.d = paramku.a((short)102, j, m, 0);
        jm.e = paramku.a((short)103, j, m, 0);
        jm.f = paramku.a((short)104, j, m, 0);
        jm.g = paramku.a((short)105, j, m, 0);
        jm.h = (paramku.a((short)101, j, m, (byte)0) == 1);
        jm.i = paramku.a((short)4, j, m, 0);
        if (jm.i != 0)
          a.a(new Integer(jm.i)); 
        arrayOfJm[k] = jm;
        j = m;
      } 
      for (k = 0; k < arrayOfJm.length - 1; k++) {
        for (int m = k + 1; m < arrayOfJm.length; m++) {
          if ((arrayOfJm[k]).c > (arrayOfJm[m]).c) {
            jm jm = arrayOfJm[k];
            arrayOfJm[k] = arrayOfJm[m];
            arrayOfJm[m] = jm;
          } 
        } 
      } 
      jn.l = arrayOfJm;
      k = paramku.a(paramku.b((short)6, 0), 0);
      int[] arrayOfInt1 = new int[a.d()];
      for (byte b1 = 0; b1 < arrayOfInt1.length; b1++)
        arrayOfInt1[b1] = ((Integer)a.b(b1)).intValue(); 
      int[] arrayOfInt2;
      if ((arrayOfInt2 = new int[paramku.b((short)154)]).length > 0) {
        j = paramku.b((short)154, 0);
        for (byte b2 = 0; b2 < arrayOfInt2.length; b2++) {
          int m = paramku.a((short)154, j);
          arrayOfInt2[b2] = paramku.a(j, 0);
          j = m;
        } 
      } 
      int i = paramku.a(paramku.b((short)6, 1), 0);
      this.b.a(jn, arrayOfInt1, k, arrayOfInt2, i);
      return;
    } catch (OutOfMemoryError outOfMemoryError) {
      return;
    } 
  }
  
  private void e(ku paramku) {
    byte b1 = 0;
    byte b2 = 0;
    byte b3 = 0;
    byte b4 = 0;
    byte b5 = 0;
    byte b6 = 0;
    int i;
    df[] arrayOfDf1 = new df[i = paramku.b((short)90)];
    byte[] arrayOfByte = new byte[i];
    int j = paramku.b((short)90, 0);
    byte b7;
    for (b7 = 0; b7 < i; b7++) {
      int k = paramku.a((short)90, j);
      int m = paramku.a(j, 0);
      arrayOfByte[b7] = paramku.a((short)91, j, k, (byte)0);
      df df;
      (df = new df(m)).b = paramku.d((short)92, j, k);
      df.c = paramku.a((short)16, j, k, (byte)0);
      int n = paramku.a((short)93, j, k, 0);
      String str = paramku.d((short)94, j, k);
      byte[] arrayOfByte1 = paramku.c((short)95, j, k);
      df.d = new dg(n, arrayOfByte1);
      df.d.b = str;
      df.e = df.d;
      df.f = new dg[paramku.a((short)96, j, k)];
      df.f[0] = df.d;
      j = paramku.a((short)96, j);
      byte b14 = 1;
      for (byte b15 = 0; b15 < df.f.length; b15++) {
        int i2 = paramku.a((short)96, j);
        int i3 = paramku.a(j, 0);
        String str1 = paramku.d((short)97, j, i2);
        byte[] arrayOfByte2 = paramku.c((short)98, j, i2);
        if (i3 != n) {
          df.f[b14] = new dg(i3, arrayOfByte2);
          (df.f[b14]).b = str1;
          b14++;
        } 
        int i1 = i2;
      } 
      if (df.c == 0) {
        switch (arrayOfByte[b7]) {
          case 0:
            b2++;
            break;
          case 1:
            b1++;
            break;
          case 2:
            b3++;
            break;
        } 
      } else {
        switch (arrayOfByte[b7]) {
          case 0:
            b5++;
            break;
          case 1:
            b4++;
            break;
          case 2:
            b6++;
            break;
        } 
      } 
      arrayOfDf1[b7] = df;
      j = k;
    } 
    b7 = 0;
    byte b8 = 0;
    byte b9 = 0;
    byte b10 = 0;
    byte b11 = 0;
    byte b12 = 0;
    df[] arrayOfDf3 = new df[b1];
    df[] arrayOfDf2 = new df[b2];
    df[] arrayOfDf4 = new df[b3];
    df[] arrayOfDf5 = new df[b4];
    df[] arrayOfDf6 = new df[b5];
    df[] arrayOfDf7 = new df[b6];
    for (byte b13 = 0; b13 < arrayOfDf1.length; b13++) {
      if ((arrayOfDf1[b13]).c == 0) {
        switch (arrayOfByte[b13]) {
          case 0:
            arrayOfDf2[b8++] = arrayOfDf1[b13];
            break;
          case 1:
            arrayOfDf3[b7++] = arrayOfDf1[b13];
            break;
          case 2:
            arrayOfDf4[b9++] = arrayOfDf1[b13];
            break;
        } 
      } else {
        switch (arrayOfByte[b13]) {
          case 0:
            arrayOfDf6[b11++] = arrayOfDf1[b13];
            break;
          case 1:
            arrayOfDf5[b10++] = arrayOfDf1[b13];
            break;
          case 2:
            arrayOfDf7[b12++] = arrayOfDf1[b13];
            break;
        } 
      } 
    } 
    this.b.a(arrayOfDf2, arrayOfDf3, arrayOfDf4, arrayOfDf6, arrayOfDf5, arrayOfDf7);
  }
  
  private void f(ku paramku) {
    String str = paramku.d((short)20);
    byte b = paramku.a((short)40, (byte)3);
    jo[] arrayOfJo = new jo[paramku.b((short)9)];
    int i = paramku.b((short)9, 0);
    for (byte b1 = 0; b1 < arrayOfJo.length; b1++) {
      int j = paramku.a((short)9, i);
      jo jo;
      (jo = new jo()).a = paramku.b(i);
      jo.b = paramku.d((short)26, i, j);
      jo.d = paramku.a((short)27, i, j, 0);
      jo.c = paramku.a((short)15, i, j, (byte)0);
      jo.e = paramku.a((short)129, i, j, 0);
      jo.f = paramku.a((short)106, i, j, 0);
      jo.g = paramku.a((short)107, i, j, (byte)0);
      arrayOfJo[b1] = jo;
      i = j;
    } 
    switch (b) {
      case 0:
        this.b.b(arrayOfJo, str);
        return;
      case 1:
        this.b.c(arrayOfJo, str);
        return;
      case 3:
        this.b.a(arrayOfJo, str);
        break;
    } 
  }
  
  private void g(ku paramku) {
    ns[] arrayOfNs = new ns[paramku.b((short)77)];
    int i = paramku.b((short)77, 0);
    for (byte b = 0; b < arrayOfNs.length; b++) {
      int j = paramku.a((short)77, i);
      String str1 = paramku.b(i);
      String str2 = paramku.d((short)26, i, j);
      i = (paramku.a((short)100, i, j, (byte)0) == 1) ? 1 : 0;
      arrayOfNs[b] = new ns(str1, str2, "", 0L);
      (arrayOfNs[b]).e = i;
      i = j;
    } 
    this.b.a(arrayOfNs);
  }
  
  private void h(ku paramku) {
    String str = paramku.d((short)192);
    int i;
    if ((i = paramku.b((short)9)) > 0) {
      do[] arrayOfDo = new do[i];
      int j = paramku.b((short)9, 0);
      try {
        for (byte b = 0; b < arrayOfDo.length; b++) {
          int k = paramku.a((short)9, j);
          arrayOfDo[b] = d(paramku, j, k);
          j = k;
        } 
        this.b.a(str, arrayOfDo);
        return;
      } catch (OutOfMemoryError outOfMemoryError) {
        paramku.c = null;
        System.gc();
      } 
    } 
  }
  
  private void i(ku paramku) {
    byte b = paramku.a((short)193, (byte)0);
    int i = paramku.b((short)192, 0);
    int j;
    lr[] arrayOfLr = new lr[j = paramku.b((short)192)];
    for (byte b1 = 0; b1 < j; b1++) {
      int m = paramku.a((short)192, i);
      int i1 = m;
      int n = i;
      ku ku1;
      String str1 = (ku1 = paramku).b(n);
      String str2 = ku1.d((short)26, n, i1);
      int i2 = ku1.a((short)106, n, i1, 0);
      String str3 = ku1.d((short)1, n, i1);
      byte b3 = ku1.a((short)101, n, i1, (byte)0);
      byte b2 = ku1.a((short)143, n, i1, (byte)0);
      arrayOfLr[b1] = new lr(str1, str2, str3, i2, b3, b2);
      int k = m;
    } 
    if (b != 0) {
      this.b.b(arrayOfLr);
      return;
    } 
    this.b.a(arrayOfLr);
  }
  
  private static do d(ku paramku, int paramInt1, int paramInt2) {
    do do;
    (do = new do()).a = paramku.b(paramInt1);
    do.b = paramku.a((short)27, paramInt1, paramInt2, 0);
    do.c = paramku.a((short)24, paramInt1, paramInt2, (byte)0);
    do.d = paramku.a((short)160, paramInt1, paramInt2, 0);
    do.f = paramku.a((short)132, paramInt1, paramInt2, 0);
    return do;
  }
  
  private void j(ku paramku) {
    ct.a("[processPrepareData]======================================");
    lh lh1 = null;
    lh lh2 = null;
    byte b1 = paramku.a((short)111, (byte)0);
    byte b2 = paramku.a((short)140, (byte)0);
    boolean bool = false;
    int i = paramku.b((short)9, 0);
    for (byte b = 0; b < 2; b++) {
      int m = paramku.a((short)9, i);
      lh lh = c(paramku, i, m);
      if (b2 != 9) {
        if (lh.b.equals(go.e)) {
          lh1 = lh;
          if (lh2 == null)
            bool = true; 
        } else {
          lh2 = lh;
        } 
      } else if (lh1 == null) {
        lh1 = lh;
        ks.i = lh.b;
      } else {
        lh2 = lh;
      } 
      int k = m;
    } 
    (ks.a()).e = paramku.d((short)28);
    byte[] arrayOfByte2 = paramku.c((short)30);
    byte[] arrayOfByte3 = null;
    byte[] arrayOfByte1 = null;
    int j = paramku.b((short)35);
    byte b3;
    for (b3 = 0; b3 < j; b3++) {
      byte[] arrayOfByte = paramku.a(paramku.b((short)35, b3));
      if (arrayOfByte3 == null) {
        arrayOfByte3 = arrayOfByte;
      } else {
        arrayOfByte1 = arrayOfByte;
      } 
    } 
    b3 = paramku.a((short)70, (byte)0);
    this.b.a(lh1, lh2, bool, arrayOfByte2, arrayOfByte3, arrayOfByte1, b3, b1, b2);
  }
  
  private lm[] k(ku paramku) {
    return a(paramku, 0);
  }
  
  private static lm[] a(ku paramku, int paramInt) {
    lm[] arrayOfLm = new lm[paramku.b((short)114) - paramInt];
    paramInt = paramku.b((short)114, paramInt);
    for (byte b = 0; b < arrayOfLm.length; b++) {
      int i = paramku.a((short)114, paramInt);
      int j = paramku.a(paramInt, 0);
      arrayOfLm[b] = new lm(j);
      (arrayOfLm[b]).b = paramku.d((short)26, paramInt, i);
      (arrayOfLm[b]).d = paramku.d((short)117, paramInt, i);
      (arrayOfLm[b]).g = paramku.a((short)106, paramInt, i, 0);
      (arrayOfLm[b]).e = paramku.a((short)122, paramInt, i, (byte)-1);
      (arrayOfLm[b]).f = paramku.a((short)123, paramInt, i, (byte)-1);
      (arrayOfLm[b]).j = paramku.a((short)4, paramInt, i, 0);
      (arrayOfLm[b]).h = paramku.a((short)145, paramInt, i, 0);
      (arrayOfLm[b]).i = paramku.a((short)106, paramInt, i, 0);
      (arrayOfLm[b]).l = paramku.a((short)82, paramInt, i, -1);
      (arrayOfLm[b]).k = paramku.a((short)132, paramInt, i, 0L);
      (arrayOfLm[b]).m = paramku.a((short)85, paramInt, i, (byte)1);
      paramInt = i;
    } 
    return arrayOfLm;
  }
  
  private void l(ku paramku) {
    int i = paramku.c((short)41, 0);
    byte[] arrayOfByte1 = paramku.c((short)30);
    byte[] arrayOfByte2 = paramku.c((short)35);
    byte[] arrayOfByte3 = paramku.a(paramku.b((short)35, 1));
    lh[] arrayOfLh1 = new lh[1];
    lh[] arrayOfLh2 = new lh[1];
    int j = paramku.b((short)9, 0);
    for (byte b = 0; b < 2; b++) {
      int m = paramku.a((short)9, j);
      lh lh = b(paramku, j, m);
      if (oq.o != 9) {
        if (lh.b.equals(go.e)) {
          arrayOfLh1[0] = lh;
        } else {
          arrayOfLh2[0] = lh;
        } 
      } else if (arrayOfLh1[0] == null) {
        arrayOfLh1[0] = lh;
      } else {
        arrayOfLh2[0] = lh;
      } 
      int k = m;
    } 
    paramku.a((short)133, (byte)0);
    boolean bool = (paramku.c((short)32) != null) ? true : false;
    if (this.c != null)
      this.c.a(arrayOfByte1, arrayOfByte2, arrayOfByte3, arrayOfLh1, arrayOfLh2, bool, i); 
  }
  
  private void a(ku paramku, nq paramnq) {
    if (this.c == null)
      return; 
    int i = paramku.b((short)35);
    paramnq.g = new byte[i][];
    for (byte b = 0; b < i; b++) {
      byte[] arrayOfByte;
      if ((arrayOfByte = paramku.a(paramku.b((short)35, b))) != null)
        paramnq.g[b] = arrayOfByte; 
    } 
    byte[] arrayOfByte2;
    if ((arrayOfByte2 = paramku.c((short)30)) != null)
      paramnq.h = arrayOfByte2; 
    b(paramku, paramnq);
    paramnq.D = paramku.a((short)52, (byte)0);
    paramnq.F = paramku.a((short)172, (byte)0);
    paramnq.C = paramku.a((short)133, (byte)0);
    boolean bool = (paramku.c((short)32) != null) ? true : false;
    paramnq.a = paramku.d((short)62);
    byte[] arrayOfByte1;
    if ((arrayOfByte1 = paramku.c((short)39)) != null) {
      this.c.a(paramnq);
      paramnq.E = true;
      a(paramku, arrayOfByte1[0], paramnq.b);
      return;
    } 
    paramnq.d = bool;
    this.c.a(paramnq);
  }
  
  private static void b(ku paramku, nq paramnq) {
    int i = paramku.b((short)9);
    int j = paramku.b((short)9, 0);
    paramnq.f = new nl[i];
    for (byte b = 0; b < i; b++) {
      int k = paramku.a((short)9, j);
      String str = paramku.b(j);
      int m = paramku.a((short)46, j, k, -1);
      byte b1 = paramku.a((short)19, j, k, (byte)0);
      int n = paramku.a((short)17, j, k, -1);
      int i1 = paramku.a((short)18, j, k, -1);
      j = paramku.a((short)45, j, k, -1);
      paramnq.f[b] = new nl(str, m, n, i1, j, b1);
      j = k;
      ct.a((String)paramnq.f[b]);
    } 
  }
  
  private void m(ku paramku) {
    int i = paramku.c((short)41, 0);
    nq nq1;
    (nq1 = new nq(i, (byte)5)).i = paramku.a((short)44, 0L);
    int j = paramku.a(paramku.b((short)64, 0), -1);
    int k = paramku.a(paramku.b((short)75, 0), 0);
    byte[] arrayOfByte1 = new byte[0];
    byte[] arrayOfByte2 = new byte[0];
    int n;
    if ((n = paramku.b((short)50)) > 0) {
      arrayOfByte1 = new byte[n];
      arrayOfByte2 = new byte[n];
      int i2 = paramku.b((short)50, 0);
      for (byte b = 0; b < n; b++) {
        int i3 = paramku.a((short)50, i2);
        arrayOfByte1[b] = (byte)paramku.a(i2, -1);
        arrayOfByte2[b] = (byte)paramku.a((short)51, i2, i3, -1);
        i2 = i3;
      } 
    } 
    byte[] arrayOfByte4 = new byte[0];
    byte[] arrayOfByte5 = new byte[0];
    int i1;
    if ((i1 = paramku.b((short)33)) > 0) {
      arrayOfByte4 = new byte[i1];
      arrayOfByte5 = new byte[i1];
      n = paramku.b((short)33, 0);
      for (byte b = 0; b < i1; b++) {
        int i2 = paramku.a((short)33, n);
        arrayOfByte4[b] = (byte)paramku.a(n, -1);
        arrayOfByte5[b] = (byte)paramku.a((short)34, n, i2, -1);
        n = i2;
      } 
    } 
    arrayOfByte5 = arrayOfByte2;
    arrayOfByte4 = arrayOfByte1;
    byte[] arrayOfByte3 = arrayOfByte5;
    arrayOfByte2 = arrayOfByte4;
    int m = k;
    k = j;
    nq nq2;
    (nq2 = nq1).n = k;
    nq2.r = m;
    nq2.s = arrayOfByte2;
    nq2.o = arrayOfByte3;
    nq2.p = arrayOfByte5;
    nq2.q = arrayOfByte4;
    a(paramku, nq1);
  }
  
  private void a(ku paramku, byte paramByte, int paramInt) {
    nq nq = new nq(paramInt, (byte)8);
    int i = paramku.c((short)42, 0);
    int j = paramku.c((short)43, 0);
    int k = paramku.c((short)110, 0);
    int[] arrayOfInt1;
    int[] arrayOfInt2 = new int[(arrayOfInt1 = new int[paramku.b((short)73)]).length];
    for (byte b1 = 0; b1 < arrayOfInt2.length; b1++) {
      arrayOfInt1[b1] = paramku.a(paramku.b((short)73, b1), -1);
      arrayOfInt2[b1] = paramku.a(paramku.b((short)74, b1), -1);
    } 
    ll[] arrayOfLl = new ll[paramku.b((short)83)];
    int m = paramku.b((short)83, 0);
    for (byte b2 = 0; b2 < arrayOfLl.length; b2++) {
      int n = paramku.a((short)83, m);
      arrayOfLl[b2] = a(paramku, m, n, true);
      m = n;
    } 
    ku ku1 = paramku;
    ky ky1 = this;
    lm[] arrayOfLm = a(ku1, 0);
    if (this.c != null) {
      lm[] arrayOfLm1 = arrayOfLm;
      arrayOfLl = arrayOfLl;
      arrayOfInt2 = arrayOfInt2;
      arrayOfInt1 = arrayOfInt1;
      boolean bool = false;
      k = j;
      j = k;
      i = i;
      paramByte = paramByte;
      nq nq1;
      (nq1 = nq).t = paramByte;
      nq1.A = arrayOfLl;
      nq1.v = j;
      nq1.u = i;
      nq1.w = k;
      nq1.x = 0;
      nq1.y = arrayOfInt1;
      nq1.z = arrayOfInt2;
      nq1.B = arrayOfLm1;
      this.c.a(nq);
    } 
  }
  
  private void n(ku paramku) {
    String str1 = paramku.d((short)77);
    String str2 = paramku.d((short)26);
    String str3 = paramku.d((short)79);
    long l = paramku.a((short)132, 0L);
    boolean bool = (paramku.a((short)100, (byte)0) == 0) ? true : false;
    ns ns = new ns(str1, str2, str3, l);
    int i;
    if ((i = paramku.b((short)80)) > 0) {
      nt[] arrayOfNt2 = new nt[i];
      int j = paramku.b((short)80, 0);
      for (byte b = 0; b < arrayOfNt2.length; b++) {
        int m = paramku.a((short)80, j);
        int n = paramku.a(j, -1);
        String str = paramku.d((short)81, j, m);
        arrayOfNt2[b] = new nt(n, str, null, str1);
        int k = m;
      } 
      nt[] arrayOfNt1 = arrayOfNt2;
      ns ns1;
      (ns1 = ns).f = arrayOfNt1;
    } 
    this.b.a(ns, bool);
  }
  
  private static void o(ku paramku) {
    String str = paramku.d((short)77);
    ns ns = new ns(str, "", "", 0L);
    int i;
    if ((i = paramku.b((short)80)) > 0) {
      nt[] arrayOfNt2 = new nt[i];
      int j = paramku.b((short)80, 0);
      for (byte b = 0; b < arrayOfNt2.length; b++) {
        int m = paramku.a((short)80, j);
        int n = paramku.a(j, -1);
        String str1 = paramku.d((short)81, j, m);
        arrayOfNt2[b] = new nt(n, str1, null, str);
        int k = m;
      } 
      nt[] arrayOfNt1 = arrayOfNt2;
      ns ns1;
      (ns1 = ns).f = arrayOfNt1;
    } 
    nu.b(ns);
  }
  
  private void p(ku paramku) {
    String str1 = paramku.d((short)77);
    String str2 = paramku.d((short)26);
    String[] arrayOfString2 = new String[paramku.b((short)1)];
    int i = paramku.b((short)1, 0);
    for (byte b = 0; b < arrayOfString2.length; b++) {
      int j = paramku.a((short)1, i);
      arrayOfString2[b] = paramku.b(i);
      i = j;
    } 
    String[] arrayOfString1 = arrayOfString2;
    ns ns1;
    ns ns2;
    (ns1 = ns2 = new ns(str1, str2, "", 0L)).g = arrayOfString1;
    nu.a(ns2);
    String str3 = paramku.d((short)149);
    this.b.a(str3, (byte)0);
  }
  
  private void q(ku paramku) {
    int i;
    lw[] arrayOfLw = new lw[i = paramku.b((short)64)];
    int j = paramku.b((short)64, 0);
    for (byte b = 0; b < i; b++) {
      int k = paramku.a((short)64, j);
      arrayOfLw[b] = new lw(paramku.a(j, 0));
      (arrayOfLw[b]).b = paramku.d((short)26, j, k);
      (arrayOfLw[b]).d = paramku.a((short)136, j, k, 0);
      lx[] arrayOfLx = new lx[paramku.a((short)67, j, k)];
      j = paramku.a((short)67, j);
      byte b1;
      for (b1 = 0; b1 < arrayOfLx.length; b1++) {
        int m = paramku.a((short)67, j);
        arrayOfLx[b1] = new lx((arrayOfLw[b]).a);
        (arrayOfLx[b1]).a = paramku.a(j, 0);
        (arrayOfLx[b1]).e = paramku.d((short)66, j, m);
        (arrayOfLx[b1]).c = paramku.a((short)76, j, m, 0);
        (arrayOfLx[b1]).b = paramku.a((short)135, j, m, 0);
        (arrayOfLx[b1]).d = paramku.a((short)68, j, m, 0);
        j = m;
      } 
      for (b1 = 0; b1 < arrayOfLx.length; b1++) {
        for (int m = b1 + 1; m < arrayOfLx.length; m++) {
          if ((arrayOfLx[b1]).a > (arrayOfLx[m]).a) {
            lx lx = arrayOfLx[b1];
            arrayOfLx[b1] = arrayOfLx[m];
            arrayOfLx[m] = lx;
          } 
        } 
      } 
      (arrayOfLw[b]).c = arrayOfLx;
      j = k;
    } 
    this.b.a(arrayOfLw);
  }
  
  private void r(ku paramku) {
    paramku.d((short)9);
    ll[] arrayOfLl;
    if ((arrayOfLl = new ll[paramku.b((short)83)]).length > 0) {
      int k = paramku.b((short)83, 0);
      for (byte b = 0; b < arrayOfLl.length; b++) {
        int m;
        if ((m = paramku.a((short)83, k)) < 0)
          m = paramku.a((short)114, k); 
        arrayOfLl[b] = a(paramku, k, m, true);
        k = m;
      } 
    } 
    ku ku1 = paramku;
    ky ky1 = this;
    lm[] arrayOfLm = a(ku1, 0);
    int i = paramku.c((short)86, 0);
    int j = paramku.c((short)145, 0);
    this.b.a(arrayOfLl, arrayOfLm, i, j);
  }
  
  private void s(ku paramku) {
    // Byte code:
    //   0: aload_1
    //   1: sipush #147
    //   4: iconst_m1
    //   5: invokevirtual a : (SB)B
    //   8: dup
    //   9: istore_2
    //   10: tableswitch default -> 572, 0 -> 64, 1 -> 100, 2 -> 353, 3 -> 259, 4 -> 160, 5 -> 416, 6 -> 434, 7 -> 535, 8 -> 545, 9 -> 555
    //   64: aload_1
    //   65: bipush #9
    //   67: invokevirtual d : (S)Ljava/lang/String;
    //   70: astore_2
    //   71: aload_1
    //   72: sipush #150
    //   75: invokevirtual d : (S)Ljava/lang/String;
    //   78: astore_3
    //   79: invokestatic a : ()Lks;
    //   82: getfield g : La;
    //   85: aload_3
    //   86: invokevirtual a : (Ljava/lang/Object;)V
    //   89: aload_0
    //   90: getfield b : Lkq;
    //   93: aload_2
    //   94: invokeinterface k : (Ljava/lang/String;)V
    //   99: return
    //   100: aload_1
    //   101: bipush #9
    //   103: invokevirtual d : (S)Ljava/lang/String;
    //   106: astore_2
    //   107: aload_1
    //   108: sipush #150
    //   111: invokevirtual d : (S)Ljava/lang/String;
    //   114: astore_3
    //   115: aload_1
    //   116: bipush #31
    //   118: iconst_m1
    //   119: invokevirtual a : (SB)B
    //   122: dup
    //   123: istore_1
    //   124: ifne -> 138
    //   127: aload_0
    //   128: getfield b : Lkq;
    //   131: aload_2
    //   132: invokeinterface m : (Ljava/lang/String;)V
    //   137: return
    //   138: aload_0
    //   139: getfield b : Lkq;
    //   142: aload_2
    //   143: invokeinterface n : (Ljava/lang/String;)V
    //   148: invokestatic a : ()Lks;
    //   151: aload_3
    //   152: putfield f : Ljava/lang/String;
    //   155: iconst_0
    //   156: putstatic ks.j : I
    //   159: return
    //   160: aload_1
    //   161: bipush #9
    //   163: invokevirtual d : (S)Ljava/lang/String;
    //   166: astore_2
    //   167: aload_1
    //   168: bipush #41
    //   170: iconst_0
    //   171: invokevirtual c : (SI)I
    //   174: putstatic ks.j : I
    //   177: aload_2
    //   178: invokestatic a : ()Lks;
    //   181: getfield c : Ljava/lang/String;
    //   184: invokevirtual equals : (Ljava/lang/Object;)Z
    //   187: ifeq -> 200
    //   190: aload_0
    //   191: getfield b : Lkq;
    //   194: invokeinterface K : ()V
    //   199: return
    //   200: aload_1
    //   201: bipush #106
    //   203: iconst_m1
    //   204: invokevirtual c : (SI)I
    //   207: istore #7
    //   209: aload_1
    //   210: bipush #83
    //   212: invokevirtual d : (S)Ljava/lang/String;
    //   215: astore #8
    //   217: iload #7
    //   219: ifle -> 247
    //   222: aload_1
    //   223: aload_1
    //   224: bipush #83
    //   226: iconst_0
    //   227: invokevirtual b : (SI)I
    //   230: iconst_m1
    //   231: iconst_1
    //   232: invokestatic a : (Lku;IIZ)Lll;
    //   235: astore_2
    //   236: aload_0
    //   237: getfield b : Lkq;
    //   240: aload_2
    //   241: invokeinterface b : (Lll;)V
    //   246: return
    //   247: aload_0
    //   248: getfield b : Lkq;
    //   251: aload #8
    //   253: invokeinterface j : (Ljava/lang/String;)V
    //   258: return
    //   259: aload_1
    //   260: bipush #9
    //   262: invokevirtual d : (S)Ljava/lang/String;
    //   265: astore_2
    //   266: aload_1
    //   267: bipush #41
    //   269: iconst_0
    //   270: invokevirtual c : (SI)I
    //   273: putstatic ks.j : I
    //   276: aload_2
    //   277: invokestatic a : ()Lks;
    //   280: getfield c : Ljava/lang/String;
    //   283: invokevirtual equals : (Ljava/lang/Object;)Z
    //   286: ifeq -> 299
    //   289: aload_0
    //   290: getfield b : Lkq;
    //   293: invokeinterface K : ()V
    //   298: return
    //   299: aload_0
    //   300: aload_1
    //   301: astore_3
    //   302: astore_2
    //   303: aload_3
    //   304: iconst_0
    //   305: invokestatic a : (Lku;I)[Llm;
    //   308: astore #7
    //   310: aload_1
    //   311: bipush #106
    //   313: iconst_m1
    //   314: invokevirtual c : (SI)I
    //   317: dup
    //   318: istore #8
    //   320: ifle -> 339
    //   323: aload_0
    //   324: getfield b : Lkq;
    //   327: aload #7
    //   329: iconst_0
    //   330: aaload
    //   331: iload #8
    //   333: invokeinterface a : (Llm;I)V
    //   338: return
    //   339: aload_0
    //   340: getfield b : Lkq;
    //   343: aload #7
    //   345: iconst_0
    //   346: aaload
    //   347: invokeinterface a : (Llm;)V
    //   352: return
    //   353: aload_1
    //   354: bipush #9
    //   356: invokevirtual d : (S)Ljava/lang/String;
    //   359: astore_2
    //   360: aload_1
    //   361: bipush #41
    //   363: iconst_0
    //   364: invokevirtual c : (SI)I
    //   367: putstatic ks.j : I
    //   370: aload_2
    //   371: invokestatic a : ()Lks;
    //   374: getfield c : Ljava/lang/String;
    //   377: invokevirtual equals : (Ljava/lang/Object;)Z
    //   380: ifeq -> 393
    //   383: aload_0
    //   384: getfield b : Lkq;
    //   387: invokeinterface K : ()V
    //   392: return
    //   393: aload_1
    //   394: sipush #132
    //   397: lconst_0
    //   398: invokevirtual a : (SJ)J
    //   401: lstore #7
    //   403: aload_0
    //   404: getfield b : Lkq;
    //   407: lload #7
    //   409: l2i
    //   410: invokeinterface l : (I)V
    //   415: return
    //   416: aload_1
    //   417: bipush #9
    //   419: invokevirtual d : (S)Ljava/lang/String;
    //   422: astore_2
    //   423: aload_0
    //   424: getfield b : Lkq;
    //   427: aload_2
    //   428: invokeinterface i : (Ljava/lang/String;)V
    //   433: return
    //   434: aload_1
    //   435: sipush #132
    //   438: ldc2_w -1
    //   441: invokevirtual a : (SJ)J
    //   444: l2i
    //   445: istore #7
    //   447: aload_1
    //   448: bipush #83
    //   450: invokevirtual b : (S)I
    //   453: anewarray ll
    //   456: dup
    //   457: astore #8
    //   459: arraylength
    //   460: ifle -> 510
    //   463: aload_1
    //   464: bipush #83
    //   466: iconst_0
    //   467: invokevirtual b : (SI)I
    //   470: istore_2
    //   471: iconst_0
    //   472: istore_3
    //   473: goto -> 503
    //   476: aload_1
    //   477: bipush #83
    //   479: iload_2
    //   480: invokevirtual a : (SI)I
    //   483: istore #4
    //   485: aload #8
    //   487: iload_3
    //   488: aload_1
    //   489: iload_2
    //   490: iload #4
    //   492: iconst_1
    //   493: invokestatic a : (Lku;IIZ)Lll;
    //   496: aastore
    //   497: iload #4
    //   499: istore_2
    //   500: iinc #3, 1
    //   503: iload_3
    //   504: aload #8
    //   506: arraylength
    //   507: if_icmplt -> 476
    //   510: aload_0
    //   511: aload_1
    //   512: astore_3
    //   513: astore_2
    //   514: aload_3
    //   515: iconst_0
    //   516: invokestatic a : (Lku;I)[Llm;
    //   519: astore_2
    //   520: aload_0
    //   521: getfield b : Lkq;
    //   524: aload #8
    //   526: aload_2
    //   527: iload #7
    //   529: invokeinterface a : ([Lll;[Llm;I)V
    //   534: return
    //   535: aload_0
    //   536: getfield b : Lkq;
    //   539: invokeinterface P : ()V
    //   544: return
    //   545: aload_0
    //   546: getfield b : Lkq;
    //   549: invokeinterface O : ()V
    //   554: return
    //   555: aload_1
    //   556: bipush #9
    //   558: invokevirtual d : (S)Ljava/lang/String;
    //   561: astore_2
    //   562: aload_0
    //   563: getfield b : Lkq;
    //   566: aload_2
    //   567: invokeinterface l : (Ljava/lang/String;)V
    //   572: return
  }
  
  private void t(ku paramku) {
    int i;
    if ((i = paramku.b((short)147)) > 0) {
      int[] arrayOfInt = new int[i];
      String[] arrayOfString = new String[i];
      int j = paramku.b((short)147, 0);
      for (byte b = 0; b < arrayOfInt.length; b++) {
        int k = paramku.a((short)147, j);
        arrayOfInt[b] = paramku.a(j, (byte)0);
        arrayOfString[b] = paramku.d((short)168, j, k);
        j = k;
      } 
      this.b.a(arrayOfInt, arrayOfString);
    } 
  }
  
  private static lb e(ku paramku, int paramInt1, int paramInt2) {
    lb lb;
    (lb = new lb()).a = paramku.a((short)118, paramInt1, paramInt2, 0);
    lb.b = paramku.a((short)119, paramInt1, paramInt2, 0);
    lb.c = paramku.a((short)120, paramInt1, paramInt2, 0);
    lb.d = paramku.a((short)121, paramInt1, paramInt2, 0);
    lb.e = paramku.a((short)72, paramInt1, paramInt2, 0);
    lb.f = paramku.a((short)71, paramInt1, paramInt2, 0);
    lb.g = paramku.a((short)126, paramInt1, paramInt2, 0);
    lb.h = paramku.a((short)124, paramInt1, paramInt2, 0);
    lb.i = paramku.a((short)47, paramInt1, paramInt2, 0);
    lb.j = paramku.a((short)200, paramInt1, paramInt2, 0);
    lb.k = paramku.a((short)201, paramInt1, paramInt2, 0);
    lb.l = paramku.a((short)202, paramInt1, paramInt2, 0);
    lb.m = paramku.a((short)203, paramInt1, paramInt2, 0);
    lb.n = paramku.a((short)204, paramInt1, paramInt2, 0);
    lb.o = paramku.a((short)221, paramInt1, paramInt2, 0);
    return lb;
  }
  
  private lq[] u(ku paramku) {
    lq[] arrayOfLq = new lq[paramku.b((short)175)];
    int i = paramku.b((short)175, 0);
    for (byte b = 0; b < arrayOfLq.length; b++) {
      byte b1;
      ll ll;
      int m;
      lm lm;
      int k;
      lu lu;
      int j = paramku.a((short)175, i);
      lq lq;
      (lq = new lq()).b = paramku.b(i);
      lq.c = paramku.a((short)159, i, j, (byte)-1);
      lq.f = paramku.d((short)62, i, j);
      lq.d = paramku.a((short)145, i, j, -1);
      lq.g = paramku.a((short)157, i, j, 0L);
      switch (lq.c) {
        case 0:
          b1 = paramku.a((short)84, i, j, (byte)0);
          (ll = new ll("", b1)).b = paramku.a(i, 0);
          ll.n = paramku.a((short)4, i, j, 0);
          ll.j = paramku.a((short)27, i, j, 0);
          ll.l = paramku.a((short)145, i, j, 0);
          ll.d = paramku.d((short)26, i, j);
          ll.i = paramku.a((short)135, i, j, -1);
          ll.f = paramku.a((short)15, i, j, (byte)7);
          ll.h = paramku.a((short)16, i, j, (byte)0);
          ll.m = paramku.a((short)138, i, j, (byte)0);
          ll.p = paramku.a((short)139, i, j, 0);
          ll.q = paramku.a((short)144, i, j, 0);
          ll.g = paramku.d((short)117, i, j);
          ll.k = paramku.a((short)190, i, j, (byte)-1);
          ll.t = paramku.a((short)85, i, j, (byte)1);
          ll.r = e(paramku, i, j);
          lq.e = ll;
          break;
        case 1:
          m = paramku.a((short)114, i, j, -1);
          (lm = new lm(m)).b = paramku.d((short)26, i, j);
          lm.d = paramku.d((short)117, i, j);
          lm.g = paramku.a((short)106, i, j, 0);
          lm.e = paramku.a((short)122, i, j, (byte)-1);
          lm.f = paramku.a((short)123, i, j, (byte)-1);
          lm.j = paramku.a((short)4, i, j, 0);
          lm.h = paramku.a((short)145, i, j, 0);
          lm.i = paramku.a((short)106, i, j, 0);
          lm.l = paramku.a((short)82, i, j, -1);
          lm.k = paramku.a((short)132, i, j, 0L);
          lm.m = paramku.a((short)85, i, j, (byte)1);
          lq.e = lm;
          break;
        case 99:
          k = paramku.a((short)155, i, j, -1);
          (lu = new lu(k)).a = paramku.d((short)26, i, j);
          lu.b = paramku.d((short)1, i, j);
          lu.c = paramku.a((short)145, i, j, 0);
          lq.e = lu;
          break;
      } 
      arrayOfLq[b] = lq;
      i = j;
    } 
    return arrayOfLq;
  }
  
  private void v(ku paramku) {
    ky ky1;
    lq[] arrayOfLq;
    If1[] arrayOfLf;
    ku ku1;
    int i;
    int j;
    boolean bool;
    byte b;
    switch (b = paramku.a((short)147, (byte)-1)) {
      case 0:
        if ((arrayOfLf = new If1[paramku.b((short)152)]).length > 0) {
          int k = paramku.b((short)152, 0);
          for (byte b1 = 0; b1 < arrayOfLf.length; b1++) {
            int m = paramku.a((short)152, k);
            byte b2 = paramku.a(k, (byte)-1);
            String str = paramku.d((short)26, k, m);
            k = paramku.a((short)106, k, m, 0);
            arrayOfLf[b1] = new If1(b2, str, k);
            k = m;
          } 
        } 
        this.b.a(arrayOfLf);
        return;
      case 1:
        ku1 = paramku;
        ky1 = this;
        arrayOfLq = new lq[ku1.b((short)153)];
        j = ku1.b((short)153, 0);
        bool = false;
      case 2:
        if ((i = arrayOfLq.b((short)114)) > 0) {
          int[] arrayOfInt1 = new int[i];
          int[] arrayOfInt2 = new int[i];
          for (byte b1 = 0; b1 < i; b1++) {
            arrayOfInt1[b1] = arrayOfLq.a(arrayOfLq.b((short)114, b1), -1);
            arrayOfInt2[b1] = arrayOfLq.a(arrayOfLq.b((short)106, b1), -1);
          } 
          this.b.a(arrayOfInt1, arrayOfInt2);
        } 
        if ((i = arrayOfLq.b((short)83)) > 0) {
          String[] arrayOfString = new String[i];
          int[] arrayOfInt = new int[i];
          for (byte b1 = 0; b1 < i; b1++) {
            arrayOfString[b1] = arrayOfLq.b(arrayOfLq.b((short)83, b1));
            arrayOfInt[b1] = arrayOfLq.a(arrayOfLq.b((short)146, b1), -1);
          } 
          this.b.a(arrayOfString, arrayOfInt);
        } 
        break;
    } 
  }
  
  private void w(ku paramku) {
    byte b = paramku.a((short)208, (byte)0);
    int i;
    dh[] arrayOfDh = new dh[i = paramku.b((short)9)];
    if (i > 0) {
      int j = paramku.b((short)9, 0);
      for (byte b2 = 0; b2 < arrayOfDh.length; b2++) {
        i = paramku.a((short)9, j);
        String str2 = paramku.b(j);
        int m = paramku.a((short)148, j, i, 0);
        String str3 = paramku.d((short)211, j, i);
        String str1 = paramku.d((short)1, j, i);
        arrayOfDh[b2] = new dh(m, str3, str2, str1);
        int k = i;
      } 
    } 
    for (byte b1 = 0; b1 < arrayOfDh.length - 1; b1++) {
      for (int j = b1 + 1; j < arrayOfDh.length; j++) {
        if ((arrayOfDh[b1]).a > (arrayOfDh[j]).a) {
          dh dh = arrayOfDh[b1];
          arrayOfDh[b1] = arrayOfDh[j];
          arrayOfDh[j] = dh;
        } 
      } 
    } 
    this.b.a(b, arrayOfDh);
  }
  
  private void x(ku paramku) {
    String str = paramku.d((short)175);
    ll[] arrayOfLl;
    if ((arrayOfLl = new ll[paramku.b((short)83)]).length > 0) {
      int i = paramku.b((short)83, 0);
      for (byte b = 0; b < arrayOfLl.length; b++) {
        int j;
        if ((j = paramku.a((short)83, i)) < 0)
          j = paramku.a((short)114, i); 
        arrayOfLl[b] = a(paramku, i, j, true);
        i = j;
      } 
    } 
    ku ku1 = paramku;
    ky ky1 = this;
    lm[] arrayOfLm = a(ku1, 0);
    this.b.a(str, arrayOfLl, arrayOfLm);
  }
  
  private void y(ku paramku) {
    If1[] arrayOfLf;
    if ((arrayOfLf = new If1[paramku.b((short)152)]).length > 0) {
      int i = paramku.b((short)152, 0);
      for (byte b = 0; b < arrayOfLf.length; b++) {
        int j = paramku.a((short)152, i);
        byte b1 = paramku.a(i, (byte)-1);
        String str = paramku.d((short)26, i, j);
        i = paramku.a((short)106, i, j, 0);
        arrayOfLf[b] = new If1(b1, str, i);
        i = j;
      } 
    } 
    this.b.b(arrayOfLf);
  }
  
  private void z(ku paramku) {
    String str = paramku.d((short)175);
    ll[] arrayOfLl;
    if ((arrayOfLl = new ll[paramku.b((short)83)]).length > 0) {
      int i = paramku.b((short)83, 0);
      for (byte b = 0; b < arrayOfLl.length; b++) {
        int j;
        if ((j = paramku.a((short)83, i)) < 0)
          j = paramku.a((short)114, i); 
        arrayOfLl[b] = a(paramku, i, j, true);
        i = j;
      } 
    } 
    ku ku1 = paramku;
    ky ky1 = this;
    lm[] arrayOfLm = a(ku1, 0);
    this.b.b(str, arrayOfLl, arrayOfLm);
  }
  
  private void A(ku paramku) {
    String str = paramku.d((short)186);
    byte b = paramku.a((short)189, (byte)-1);
    ll[] arrayOfLl = new ll[paramku.b((short)83)];
    ku ku1 = null;
    if (arrayOfLl.length > 0) {
      int i = paramku.b((short)83, 0);
      for (byte b1 = 0; b1 < arrayOfLl.length; b1++) {
        int j = paramku.a((short)83, i);
        arrayOfLl[b1] = a(paramku, i, j, true);
        i = j;
      } 
    } 
    ku1 = paramku;
    ky ky1 = this;
    lm[] arrayOfLm = a(ku1, 0);
    this.b.a(str, arrayOfLl, arrayOfLm, b);
  }
  
  private void B(ku paramku) {
    String str = paramku.d((short)186);
    byte b = paramku.a((short)189, (byte)-1);
    ll[] arrayOfLl = new ll[paramku.b((short)83)];
    ku ku1 = null;
    if (arrayOfLl.length > 0) {
      int i = paramku.b((short)83, 0);
      for (byte b1 = 0; b1 < arrayOfLl.length; b1++) {
        int j = paramku.a((short)83, i);
        arrayOfLl[b1] = a(paramku, i, j, true);
        i = j;
      } 
    } 
    ku1 = paramku;
    ky ky1 = this;
    lm[] arrayOfLm = a(ku1, 0);
    this.b.b(str, arrayOfLl, arrayOfLm, b);
  }
  
  private void C(ku paramku) {
    paramku.d((short)9);
    int i;
    String[] arrayOfString = new String[i = paramku.b((short)83)];
    int[] arrayOfInt2 = new int[i];
    int[] arrayOfInt3 = new int[i];
    int[] arrayOfInt4 = new int[i = paramku.b((short)114)];
    int[] arrayOfInt1 = new int[i];
    int j = paramku.b((short)83, 0);
    byte b;
    for (b = 0; b < arrayOfString.length; b++) {
      int k = paramku.a((short)83, j);
      arrayOfString[b] = paramku.b(j);
      arrayOfInt2[b] = paramku.a((short)139, j, k, 0);
      arrayOfInt3[b] = paramku.a((short)144, j, k, 0);
      j = k;
    } 
    j = paramku.b((short)114, 0);
    for (b = 0; b < arrayOfInt4.length; b++) {
      int k = paramku.a((short)114, j);
      arrayOfInt4[b] = paramku.a(j, 0);
      arrayOfInt1[b] = paramku.a((short)106, j, k, 0);
      j = k;
    } 
    if (this.b != null)
      this.b.a(arrayOfString, arrayOfInt2, arrayOfInt3, arrayOfInt4, arrayOfInt1); 
  }
  
  private void D(ku paramku) {
    String str2 = paramku.d((short)182);
    String str3 = paramku.d((short)183);
    String str1 = paramku.d((short)1);
    String[] arrayOfString1 = i.b(str3, ";");
    String[] arrayOfString2 = null;
    String[] arrayOfString3 = null;
    if (arrayOfString1 != null && arrayOfString1.length > 0 && arrayOfString1.length % 2 == 0) {
      arrayOfString2 = new String[arrayOfString1.length / 2];
      arrayOfString3 = new String[arrayOfString1.length / 2];
      for (byte b = 0; b < arrayOfString1.length; b += 2) {
        arrayOfString3[b / 2] = arrayOfString1[b];
        arrayOfString2[b / 2] = arrayOfString1[b + 1];
      } 
    } 
    this.b.b(str1, str2, arrayOfString3, arrayOfString2);
  }
  
  public final void a() {
    this.f = true;
    if (this.e != null) {
      kv kv1 = this.e;
      try {
        kv1.a.close();
      } catch (Throwable throwable) {}
      this.e = null;
    } 
  }
}


/* Location:              G:\DOWNLOAD\Loan 12 S Qun Online.jar!\ky.class
 * Java compiler version: 1 (45.3)
 * JD-Core Version:       1.1.3
 */